<?xml version="1.0" encoding="UTF-8"?>
<tv generator-info-name="AlwanSportsEPG">
  <channel id="alwan_sports">
    <display-name>Alwan Sports</display-name>
    <icon src="https://raw.githubusercontent.com/ayoubboukous27/beIN-Sports-EPG-Worldwide/refs/heads/main/Logos/alwan-sports.png"/>
  </channel>
  <programme start="20260501040750 +0000" stop="20260501050750 +0000" channel="alwan_sports">
    <title>البطولات الكروية مباشرة</title>
    <desc>نقل مباشر لجميع البطولات الكروية العالمية: دوري الأبطال والدوريات الأوروبية والعالمية.</desc>
  </programme>
  <programme start="20260501050750 +0000" stop="20260501060750 +0000" channel="alwan_sports">
    <title>البطولات الكروية مباشرة</title>
    <desc>نقل مباشر لجميع البطولات الكروية العالمية: دوري الأبطال والدوريات الأوروبية والعالمية.</desc>
  </programme>
  <programme start="20260501060750 +0000" stop="20260501070750 +0000" channel="alwan_sports">
    <title>البطولات الكروية مباشرة</title>
    <desc>نقل مباشر لجميع البطولات الكروية العالمية: دوري الأبطال والدوريات الأوروبية والعالمية.</desc>
  </programme>
  <programme start="20260501070750 +0000" stop="20260501080750 +0000" channel="alwan_sports">
    <title>البطولات الكروية مباشرة</title>
    <desc>نقل مباشر لجميع البطولات الكروية العالمية: دوري الأبطال والدوريات الأوروبية والعالمية.</desc>
  </programme>
  <programme start="20260501080750 +0000" stop="20260501090750 +0000" channel="alwan_sports">
    <title>البطولات الكروية مباشرة</title>
    <desc>نقل مباشر لجميع البطولات الكروية العالمية: دوري الأبطال والدوريات الأوروبية والعالمية.</desc>
  </programme>
  <programme start="20260501090750 +0000" stop="20260501100750 +0000" channel="alwan_sports">
    <title>البطولات الكروية مباشرة</title>
    <desc>نقل مباشر لجميع البطولات الكروية العالمية: دوري الأبطال والدوريات الأوروبية والعالمية.</desc>
  </programme>
  <programme start="20260501100750 +0000" stop="20260501110750 +0000" channel="alwan_sports">
    <title>البطولات الكروية مباشرة</title>
    <desc>نقل مباشر لجميع البطولات الكروية العالمية: دوري الأبطال والدوريات الأوروبية والعالمية.</desc>
  </programme>
  <programme start="20260501110750 +0000" stop="20260501120750 +0000" channel="alwan_sports">
    <title>البطولات الكروية مباشرة</title>
    <desc>نقل مباشر لجميع البطولات الكروية العالمية: دوري الأبطال والدوريات الأوروبية والعالمية.</desc>
  </programme>
  <programme start="20260501120750 +0000" stop="20260501130750 +0000" channel="alwan_sports">
    <title>البطولات الكروية مباشرة</title>
    <desc>نقل مباشر لجميع البطولات الكروية العالمية: دوري الأبطال والدوريات الأوروبية والعالمية.</desc>
  </programme>
  <programme start="20260501130750 +0000" stop="20260501140750 +0000" channel="alwan_sports">
    <title>البطولات الكروية مباشرة</title>
    <desc>نقل مباشر لجميع البطولات الكروية العالمية: دوري الأبطال والدوريات الأوروبية والعالمية.</desc>
  </programme>
  <programme start="20260501140750 +0000" stop="20260501150750 +0000" channel="alwan_sports">
    <title>البطولات الكروية مباشرة</title>
    <desc>نقل مباشر لجميع البطولات الكروية العالمية: دوري الأبطال والدوريات الأوروبية والعالمية.</desc>
  </programme>
  <programme start="20260501150750 +0000" stop="20260501160750 +0000" channel="alwan_sports">
    <title>البطولات الكروية مباشرة</title>
    <desc>نقل مباشر لجميع البطولات الكروية العالمية: دوري الأبطال والدوريات الأوروبية والعالمية.</desc>
  </programme>
  <programme start="20260501160750 +0000" stop="20260501170750 +0000" channel="alwan_sports">
    <title>البطولات الكروية مباشرة</title>
    <desc>نقل مباشر لجميع البطولات الكروية العالمية: دوري الأبطال والدوريات الأوروبية والعالمية.</desc>
  </programme>
  <programme start="20260501170750 +0000" stop="20260501180750 +0000" channel="alwan_sports">
    <title>البطولات الكروية مباشرة</title>
    <desc>نقل مباشر لجميع البطولات الكروية العالمية: دوري الأبطال والدوريات الأوروبية والعالمية.</desc>
  </programme>
  <programme start="20260501180750 +0000" stop="20260501190750 +0000" channel="alwan_sports">
    <title>البطولات الكروية مباشرة</title>
    <desc>نقل مباشر لجميع البطولات الكروية العالمية: دوري الأبطال والدوريات الأوروبية والعالمية.</desc>
  </programme>
  <programme start="20260501190750 +0000" stop="20260501200750 +0000" channel="alwan_sports">
    <title>البطولات الكروية مباشرة</title>
    <desc>نقل مباشر لجميع البطولات الكروية العالمية: دوري الأبطال والدوريات الأوروبية والعالمية.</desc>
  </programme>
  <programme start="20260501200750 +0000" stop="20260501210750 +0000" channel="alwan_sports">
    <title>البطولات الكروية مباشرة</title>
    <desc>نقل مباشر لجميع البطولات الكروية العالمية: دوري الأبطال والدوريات الأوروبية والعالمية.</desc>
  </programme>
  <programme start="20260501210750 +0000" stop="20260501220750 +0000" channel="alwan_sports">
    <title>البطولات الكروية مباشرة</title>
    <desc>نقل مباشر لجميع البطولات الكروية العالمية: دوري الأبطال والدوريات الأوروبية والعالمية.</desc>
  </programme>
  <programme start="20260501220750 +0000" stop="20260501230750 +0000" channel="alwan_sports">
    <title>البطولات الكروية مباشرة</title>
    <desc>نقل مباشر لجميع البطولات الكروية العالمية: دوري الأبطال والدوريات الأوروبية والعالمية.</desc>
  </programme>
  <programme start="20260501230750 +0000" stop="20260502000750 +0000" channel="alwan_sports">
    <title>البطولات الكروية مباشرة</title>
    <desc>نقل مباشر لجميع البطولات الكروية العالمية: دوري الأبطال والدوريات الأوروبية والعالمية.</desc>
  </programme>
  <programme start="20260502000750 +0000" stop="20260502010750 +0000" channel="alwan_sports">
    <title>البطولات الكروية مباشرة</title>
    <desc>نقل مباشر لجميع البطولات الكروية العالمية: دوري الأبطال والدوريات الأوروبية والعالمية.</desc>
  </programme>
  <programme start="20260502010750 +0000" stop="20260502020750 +0000" channel="alwan_sports">
    <title>البطولات الكروية مباشرة</title>
    <desc>نقل مباشر لجميع البطولات الكروية العالمية: دوري الأبطال والدوريات الأوروبية والعالمية.</desc>
  </programme>
  <programme start="20260502020750 +0000" stop="20260502030750 +0000" channel="alwan_sports">
    <title>البطولات الكروية مباشرة</title>
    <desc>نقل مباشر لجميع البطولات الكروية العالمية: دوري الأبطال والدوريات الأوروبية والعالمية.</desc>
  </programme>
  <programme start="20260502030750 +0000" stop="20260502040750 +0000" channel="alwan_sports">
    <title>البطولات الكروية مباشرة</title>
    <desc>نقل مباشر لجميع البطولات الكروية العالمية: دوري الأبطال والدوريات الأوروبية والعالمية.</desc>
  </programme>
  <programme start="20260502040750 +0000" stop="20260502050750 +0000" channel="alwan_sports">
    <title>البطولات الكروية مباشرة</title>
    <desc>نقل مباشر لجميع البطولات الكروية العالمية: دوري الأبطال والدوريات الأوروبية والعالمية.</desc>
  </programme>
  <programme start="20260502050750 +0000" stop="20260502060750 +0000" channel="alwan_sports">
    <title>البطولات الكروية مباشرة</title>
    <desc>نقل مباشر لجميع البطولات الكروية العالمية: دوري الأبطال والدوريات الأوروبية والعالمية.</desc>
  </programme>
  <programme start="20260502060750 +0000" stop="20260502070750 +0000" channel="alwan_sports">
    <title>البطولات الكروية مباشرة</title>
    <desc>نقل مباشر لجميع البطولات الكروية العالمية: دوري الأبطال والدوريات الأوروبية والعالمية.</desc>
  </programme>
  <programme start="20260502070750 +0000" stop="20260502080750 +0000" channel="alwan_sports">
    <title>البطولات الكروية مباشرة</title>
    <desc>نقل مباشر لجميع البطولات الكروية العالمية: دوري الأبطال والدوريات الأوروبية والعالمية.</desc>
  </programme>
  <programme start="20260502080750 +0000" stop="20260502090750 +0000" channel="alwan_sports">
    <title>البطولات الكروية مباشرة</title>
    <desc>نقل مباشر لجميع البطولات الكروية العالمية: دوري الأبطال والدوريات الأوروبية والعالمية.</desc>
  </programme>
  <programme start="20260502090750 +0000" stop="20260502100750 +0000" channel="alwan_sports">
    <title>البطولات الكروية مباشرة</title>
    <desc>نقل مباشر لجميع البطولات الكروية العالمية: دوري الأبطال والدوريات الأوروبية والعالمية.</desc>
  </programme>
  <programme start="20260502100750 +0000" stop="20260502110750 +0000" channel="alwan_sports">
    <title>البطولات الكروية مباشرة</title>
    <desc>نقل مباشر لجميع البطولات الكروية العالمية: دوري الأبطال والدوريات الأوروبية والعالمية.</desc>
  </programme>
  <programme start="20260502110750 +0000" stop="20260502120750 +0000" channel="alwan_sports">
    <title>البطولات الكروية مباشرة</title>
    <desc>نقل مباشر لجميع البطولات الكروية العالمية: دوري الأبطال والدوريات الأوروبية والعالمية.</desc>
  </programme>
  <programme start="20260502120750 +0000" stop="20260502130750 +0000" channel="alwan_sports">
    <title>البطولات الكروية مباشرة</title>
    <desc>نقل مباشر لجميع البطولات الكروية العالمية: دوري الأبطال والدوريات الأوروبية والعالمية.</desc>
  </programme>
  <programme start="20260502130750 +0000" stop="20260502140750 +0000" channel="alwan_sports">
    <title>البطولات الكروية مباشرة</title>
    <desc>نقل مباشر لجميع البطولات الكروية العالمية: دوري الأبطال والدوريات الأوروبية والعالمية.</desc>
  </programme>
  <programme start="20260502140750 +0000" stop="20260502150750 +0000" channel="alwan_sports">
    <title>البطولات الكروية مباشرة</title>
    <desc>نقل مباشر لجميع البطولات الكروية العالمية: دوري الأبطال والدوريات الأوروبية والعالمية.</desc>
  </programme>
  <programme start="20260502150750 +0000" stop="20260502160750 +0000" channel="alwan_sports">
    <title>البطولات الكروية مباشرة</title>
    <desc>نقل مباشر لجميع البطولات الكروية العالمية: دوري الأبطال والدوريات الأوروبية والعالمية.</desc>
  </programme>
  <programme start="20260502160750 +0000" stop="20260502170750 +0000" channel="alwan_sports">
    <title>البطولات الكروية مباشرة</title>
    <desc>نقل مباشر لجميع البطولات الكروية العالمية: دوري الأبطال والدوريات الأوروبية والعالمية.</desc>
  </programme>
  <programme start="20260502170750 +0000" stop="20260502180750 +0000" channel="alwan_sports">
    <title>البطولات الكروية مباشرة</title>
    <desc>نقل مباشر لجميع البطولات الكروية العالمية: دوري الأبطال والدوريات الأوروبية والعالمية.</desc>
  </programme>
  <programme start="20260502180750 +0000" stop="20260502190750 +0000" channel="alwan_sports">
    <title>البطولات الكروية مباشرة</title>
    <desc>نقل مباشر لجميع البطولات الكروية العالمية: دوري الأبطال والدوريات الأوروبية والعالمية.</desc>
  </programme>
  <programme start="20260502190750 +0000" stop="20260502200750 +0000" channel="alwan_sports">
    <title>البطولات الكروية مباشرة</title>
    <desc>نقل مباشر لجميع البطولات الكروية العالمية: دوري الأبطال والدوريات الأوروبية والعالمية.</desc>
  </programme>
  <programme start="20260502200750 +0000" stop="20260502210750 +0000" channel="alwan_sports">
    <title>البطولات الكروية مباشرة</title>
    <desc>نقل مباشر لجميع البطولات الكروية العالمية: دوري الأبطال والدوريات الأوروبية والعالمية.</desc>
  </programme>
  <programme start="20260502210750 +0000" stop="20260502220750 +0000" channel="alwan_sports">
    <title>البطولات الكروية مباشرة</title>
    <desc>نقل مباشر لجميع البطولات الكروية العالمية: دوري الأبطال والدوريات الأوروبية والعالمية.</desc>
  </programme>
  <programme start="20260502220750 +0000" stop="20260502230750 +0000" channel="alwan_sports">
    <title>البطولات الكروية مباشرة</title>
    <desc>نقل مباشر لجميع البطولات الكروية العالمية: دوري الأبطال والدوريات الأوروبية والعالمية.</desc>
  </programme>
  <programme start="20260502230750 +0000" stop="20260503000750 +0000" channel="alwan_sports">
    <title>البطولات الكروية مباشرة</title>
    <desc>نقل مباشر لجميع البطولات الكروية العالمية: دوري الأبطال والدوريات الأوروبية والعالمية.</desc>
  </programme>
  <programme start="20260503000750 +0000" stop="20260503010750 +0000" channel="alwan_sports">
    <title>البطولات الكروية مباشرة</title>
    <desc>نقل مباشر لجميع البطولات الكروية العالمية: دوري الأبطال والدوريات الأوروبية والعالمية.</desc>
  </programme>
  <programme start="20260503010750 +0000" stop="20260503020750 +0000" channel="alwan_sports">
    <title>البطولات الكروية مباشرة</title>
    <desc>نقل مباشر لجميع البطولات الكروية العالمية: دوري الأبطال والدوريات الأوروبية والعالمية.</desc>
  </programme>
  <programme start="20260503020750 +0000" stop="20260503030750 +0000" channel="alwan_sports">
    <title>البطولات الكروية مباشرة</title>
    <desc>نقل مباشر لجميع البطولات الكروية العالمية: دوري الأبطال والدوريات الأوروبية والعالمية.</desc>
  </programme>
  <programme start="20260503030750 +0000" stop="20260503040750 +0000" channel="alwan_sports">
    <title>البطولات الكروية مباشرة</title>
    <desc>نقل مباشر لجميع البطولات الكروية العالمية: دوري الأبطال والدوريات الأوروبية والعالمية.</desc>
  </programme>
  <programme start="20260503040750 +0000" stop="20260503050750 +0000" channel="alwan_sports">
    <title>البطولات الكروية مباشرة</title>
    <desc>نقل مباشر لجميع البطولات الكروية العالمية: دوري الأبطال والدوريات الأوروبية والعالمية.</desc>
  </programme>
  <programme start="20260503050750 +0000" stop="20260503060750 +0000" channel="alwan_sports">
    <title>البطولات الكروية مباشرة</title>
    <desc>نقل مباشر لجميع البطولات الكروية العالمية: دوري الأبطال والدوريات الأوروبية والعالمية.</desc>
  </programme>
  <programme start="20260503060750 +0000" stop="20260503070750 +0000" channel="alwan_sports">
    <title>البطولات الكروية مباشرة</title>
    <desc>نقل مباشر لجميع البطولات الكروية العالمية: دوري الأبطال والدوريات الأوروبية والعالمية.</desc>
  </programme>
  <programme start="20260503070750 +0000" stop="20260503080750 +0000" channel="alwan_sports">
    <title>البطولات الكروية مباشرة</title>
    <desc>نقل مباشر لجميع البطولات الكروية العالمية: دوري الأبطال والدوريات الأوروبية والعالمية.</desc>
  </programme>
  <programme start="20260503080750 +0000" stop="20260503090750 +0000" channel="alwan_sports">
    <title>البطولات الكروية مباشرة</title>
    <desc>نقل مباشر لجميع البطولات الكروية العالمية: دوري الأبطال والدوريات الأوروبية والعالمية.</desc>
  </programme>
  <programme start="20260503090750 +0000" stop="20260503100750 +0000" channel="alwan_sports">
    <title>البطولات الكروية مباشرة</title>
    <desc>نقل مباشر لجميع البطولات الكروية العالمية: دوري الأبطال والدوريات الأوروبية والعالمية.</desc>
  </programme>
  <programme start="20260503100750 +0000" stop="20260503110750 +0000" channel="alwan_sports">
    <title>البطولات الكروية مباشرة</title>
    <desc>نقل مباشر لجميع البطولات الكروية العالمية: دوري الأبطال والدوريات الأوروبية والعالمية.</desc>
  </programme>
  <programme start="20260503110750 +0000" stop="20260503120750 +0000" channel="alwan_sports">
    <title>البطولات الكروية مباشرة</title>
    <desc>نقل مباشر لجميع البطولات الكروية العالمية: دوري الأبطال والدوريات الأوروبية والعالمية.</desc>
  </programme>
  <programme start="20260503120750 +0000" stop="20260503130750 +0000" channel="alwan_sports">
    <title>البطولات الكروية مباشرة</title>
    <desc>نقل مباشر لجميع البطولات الكروية العالمية: دوري الأبطال والدوريات الأوروبية والعالمية.</desc>
  </programme>
  <programme start="20260503130750 +0000" stop="20260503140750 +0000" channel="alwan_sports">
    <title>البطولات الكروية مباشرة</title>
    <desc>نقل مباشر لجميع البطولات الكروية العالمية: دوري الأبطال والدوريات الأوروبية والعالمية.</desc>
  </programme>
  <programme start="20260503140750 +0000" stop="20260503150750 +0000" channel="alwan_sports">
    <title>البطولات الكروية مباشرة</title>
    <desc>نقل مباشر لجميع البطولات الكروية العالمية: دوري الأبطال والدوريات الأوروبية والعالمية.</desc>
  </programme>
  <programme start="20260503150750 +0000" stop="20260503160750 +0000" channel="alwan_sports">
    <title>البطولات الكروية مباشرة</title>
    <desc>نقل مباشر لجميع البطولات الكروية العالمية: دوري الأبطال والدوريات الأوروبية والعالمية.</desc>
  </programme>
  <programme start="20260503160750 +0000" stop="20260503170750 +0000" channel="alwan_sports">
    <title>البطولات الكروية مباشرة</title>
    <desc>نقل مباشر لجميع البطولات الكروية العالمية: دوري الأبطال والدوريات الأوروبية والعالمية.</desc>
  </programme>
  <programme start="20260503170750 +0000" stop="20260503180750 +0000" channel="alwan_sports">
    <title>البطولات الكروية مباشرة</title>
    <desc>نقل مباشر لجميع البطولات الكروية العالمية: دوري الأبطال والدوريات الأوروبية والعالمية.</desc>
  </programme>
  <programme start="20260503180750 +0000" stop="20260503190750 +0000" channel="alwan_sports">
    <title>البطولات الكروية مباشرة</title>
    <desc>نقل مباشر لجميع البطولات الكروية العالمية: دوري الأبطال والدوريات الأوروبية والعالمية.</desc>
  </programme>
  <programme start="20260503190750 +0000" stop="20260503200750 +0000" channel="alwan_sports">
    <title>البطولات الكروية مباشرة</title>
    <desc>نقل مباشر لجميع البطولات الكروية العالمية: دوري الأبطال والدوريات الأوروبية والعالمية.</desc>
  </programme>
  <programme start="20260503200750 +0000" stop="20260503210750 +0000" channel="alwan_sports">
    <title>البطولات الكروية مباشرة</title>
    <desc>نقل مباشر لجميع البطولات الكروية العالمية: دوري الأبطال والدوريات الأوروبية والعالمية.</desc>
  </programme>
  <programme start="20260503210750 +0000" stop="20260503220750 +0000" channel="alwan_sports">
    <title>البطولات الكروية مباشرة</title>
    <desc>نقل مباشر لجميع البطولات الكروية العالمية: دوري الأبطال والدوريات الأوروبية والعالمية.</desc>
  </programme>
  <programme start="20260503220750 +0000" stop="20260503230750 +0000" channel="alwan_sports">
    <title>البطولات الكروية مباشرة</title>
    <desc>نقل مباشر لجميع البطولات الكروية العالمية: دوري الأبطال والدوريات الأوروبية والعالمية.</desc>
  </programme>
  <programme start="20260503230750 +0000" stop="20260504000750 +0000" channel="alwan_sports">
    <title>البطولات الكروية مباشرة</title>
    <desc>نقل مباشر لجميع البطولات الكروية العالمية: دوري الأبطال والدوريات الأوروبية والعالمية.</desc>
  </programme>
  <programme start="20260504000750 +0000" stop="20260504010750 +0000" channel="alwan_sports">
    <title>البطولات الكروية مباشرة</title>
    <desc>نقل مباشر لجميع البطولات الكروية العالمية: دوري الأبطال والدوريات الأوروبية والعالمية.</desc>
  </programme>
  <programme start="20260504010750 +0000" stop="20260504020750 +0000" channel="alwan_sports">
    <title>البطولات الكروية مباشرة</title>
    <desc>نقل مباشر لجميع البطولات الكروية العالمية: دوري الأبطال والدوريات الأوروبية والعالمية.</desc>
  </programme>
  <programme start="20260504020750 +0000" stop="20260504030750 +0000" channel="alwan_sports">
    <title>البطولات الكروية مباشرة</title>
    <desc>نقل مباشر لجميع البطولات الكروية العالمية: دوري الأبطال والدوريات الأوروبية والعالمية.</desc>
  </programme>
  <programme start="20260504030750 +0000" stop="20260504040750 +0000" channel="alwan_sports">
    <title>البطولات الكروية مباشرة</title>
    <desc>نقل مباشر لجميع البطولات الكروية العالمية: دوري الأبطال والدوريات الأوروبية والعالمية.</desc>
  </programme>
  <programme start="20260504040750 +0000" stop="20260504050750 +0000" channel="alwan_sports">
    <title>البطولات الكروية مباشرة</title>
    <desc>نقل مباشر لجميع البطولات الكروية العالمية: دوري الأبطال والدوريات الأوروبية والعالمية.</desc>
  </programme>
  <programme start="20260504050750 +0000" stop="20260504060750 +0000" channel="alwan_sports">
    <title>البطولات الكروية مباشرة</title>
    <desc>نقل مباشر لجميع البطولات الكروية العالمية: دوري الأبطال والدوريات الأوروبية والعالمية.</desc>
  </programme>
  <programme start="20260504060750 +0000" stop="20260504070750 +0000" channel="alwan_sports">
    <title>البطولات الكروية مباشرة</title>
    <desc>نقل مباشر لجميع البطولات الكروية العالمية: دوري الأبطال والدوريات الأوروبية والعالمية.</desc>
  </programme>
  <programme start="20260504070750 +0000" stop="20260504080750 +0000" channel="alwan_sports">
    <title>البطولات الكروية مباشرة</title>
    <desc>نقل مباشر لجميع البطولات الكروية العالمية: دوري الأبطال والدوريات الأوروبية والعالمية.</desc>
  </programme>
  <programme start="20260504080750 +0000" stop="20260504090750 +0000" channel="alwan_sports">
    <title>البطولات الكروية مباشرة</title>
    <desc>نقل مباشر لجميع البطولات الكروية العالمية: دوري الأبطال والدوريات الأوروبية والعالمية.</desc>
  </programme>
  <programme start="20260504090750 +0000" stop="20260504100750 +0000" channel="alwan_sports">
    <title>البطولات الكروية مباشرة</title>
    <desc>نقل مباشر لجميع البطولات الكروية العالمية: دوري الأبطال والدوريات الأوروبية والعالمية.</desc>
  </programme>
  <programme start="20260504100750 +0000" stop="20260504110750 +0000" channel="alwan_sports">
    <title>البطولات الكروية مباشرة</title>
    <desc>نقل مباشر لجميع البطولات الكروية العالمية: دوري الأبطال والدوريات الأوروبية والعالمية.</desc>
  </programme>
  <programme start="20260504110750 +0000" stop="20260504120750 +0000" channel="alwan_sports">
    <title>البطولات الكروية مباشرة</title>
    <desc>نقل مباشر لجميع البطولات الكروية العالمية: دوري الأبطال والدوريات الأوروبية والعالمية.</desc>
  </programme>
  <programme start="20260504120750 +0000" stop="20260504130750 +0000" channel="alwan_sports">
    <title>البطولات الكروية مباشرة</title>
    <desc>نقل مباشر لجميع البطولات الكروية العالمية: دوري الأبطال والدوريات الأوروبية والعالمية.</desc>
  </programme>
  <programme start="20260504130750 +0000" stop="20260504140750 +0000" channel="alwan_sports">
    <title>البطولات الكروية مباشرة</title>
    <desc>نقل مباشر لجميع البطولات الكروية العالمية: دوري الأبطال والدوريات الأوروبية والعالمية.</desc>
  </programme>
  <programme start="20260504140750 +0000" stop="20260504150750 +0000" channel="alwan_sports">
    <title>البطولات الكروية مباشرة</title>
    <desc>نقل مباشر لجميع البطولات الكروية العالمية: دوري الأبطال والدوريات الأوروبية والعالمية.</desc>
  </programme>
  <programme start="20260504150750 +0000" stop="20260504160750 +0000" channel="alwan_sports">
    <title>البطولات الكروية مباشرة</title>
    <desc>نقل مباشر لجميع البطولات الكروية العالمية: دوري الأبطال والدوريات الأوروبية والعالمية.</desc>
  </programme>
  <programme start="20260504160750 +0000" stop="20260504170750 +0000" channel="alwan_sports">
    <title>البطولات الكروية مباشرة</title>
    <desc>نقل مباشر لجميع البطولات الكروية العالمية: دوري الأبطال والدوريات الأوروبية والعالمية.</desc>
  </programme>
  <programme start="20260504170750 +0000" stop="20260504180750 +0000" channel="alwan_sports">
    <title>البطولات الكروية مباشرة</title>
    <desc>نقل مباشر لجميع البطولات الكروية العالمية: دوري الأبطال والدوريات الأوروبية والعالمية.</desc>
  </programme>
  <programme start="20260504180750 +0000" stop="20260504190750 +0000" channel="alwan_sports">
    <title>البطولات الكروية مباشرة</title>
    <desc>نقل مباشر لجميع البطولات الكروية العالمية: دوري الأبطال والدوريات الأوروبية والعالمية.</desc>
  </programme>
  <programme start="20260504190750 +0000" stop="20260504200750 +0000" channel="alwan_sports">
    <title>البطولات الكروية مباشرة</title>
    <desc>نقل مباشر لجميع البطولات الكروية العالمية: دوري الأبطال والدوريات الأوروبية والعالمية.</desc>
  </programme>
  <programme start="20260504200750 +0000" stop="20260504210750 +0000" channel="alwan_sports">
    <title>البطولات الكروية مباشرة</title>
    <desc>نقل مباشر لجميع البطولات الكروية العالمية: دوري الأبطال والدوريات الأوروبية والعالمية.</desc>
  </programme>
  <programme start="20260504210750 +0000" stop="20260504220750 +0000" channel="alwan_sports">
    <title>البطولات الكروية مباشرة</title>
    <desc>نقل مباشر لجميع البطولات الكروية العالمية: دوري الأبطال والدوريات الأوروبية والعالمية.</desc>
  </programme>
  <programme start="20260504220750 +0000" stop="20260504230750 +0000" channel="alwan_sports">
    <title>البطولات الكروية مباشرة</title>
    <desc>نقل مباشر لجميع البطولات الكروية العالمية: دوري الأبطال والدوريات الأوروبية والعالمية.</desc>
  </programme>
  <programme start="20260504230750 +0000" stop="20260505000750 +0000" channel="alwan_sports">
    <title>البطولات الكروية مباشرة</title>
    <desc>نقل مباشر لجميع البطولات الكروية العالمية: دوري الأبطال والدوريات الأوروبية والعالمية.</desc>
  </programme>
  <programme start="20260505000750 +0000" stop="20260505010750 +0000" channel="alwan_sports">
    <title>البطولات الكروية مباشرة</title>
    <desc>نقل مباشر لجميع البطولات الكروية العالمية: دوري الأبطال والدوريات الأوروبية والعالمية.</desc>
  </programme>
  <programme start="20260505010750 +0000" stop="20260505020750 +0000" channel="alwan_sports">
    <title>البطولات الكروية مباشرة</title>
    <desc>نقل مباشر لجميع البطولات الكروية العالمية: دوري الأبطال والدوريات الأوروبية والعالمية.</desc>
  </programme>
  <programme start="20260505020750 +0000" stop="20260505030750 +0000" channel="alwan_sports">
    <title>البطولات الكروية مباشرة</title>
    <desc>نقل مباشر لجميع البطولات الكروية العالمية: دوري الأبطال والدوريات الأوروبية والعالمية.</desc>
  </programme>
  <programme start="20260505030750 +0000" stop="20260505040750 +0000" channel="alwan_sports">
    <title>البطولات الكروية مباشرة</title>
    <desc>نقل مباشر لجميع البطولات الكروية العالمية: دوري الأبطال والدوريات الأوروبية والعالمية.</desc>
  </programme>
  <programme start="20260505040750 +0000" stop="20260505050750 +0000" channel="alwan_sports">
    <title>البطولات الكروية مباشرة</title>
    <desc>نقل مباشر لجميع البطولات الكروية العالمية: دوري الأبطال والدوريات الأوروبية والعالمية.</desc>
  </programme>
  <programme start="20260505050750 +0000" stop="20260505060750 +0000" channel="alwan_sports">
    <title>البطولات الكروية مباشرة</title>
    <desc>نقل مباشر لجميع البطولات الكروية العالمية: دوري الأبطال والدوريات الأوروبية والعالمية.</desc>
  </programme>
  <programme start="20260505060750 +0000" stop="20260505070750 +0000" channel="alwan_sports">
    <title>البطولات الكروية مباشرة</title>
    <desc>نقل مباشر لجميع البطولات الكروية العالمية: دوري الأبطال والدوريات الأوروبية والعالمية.</desc>
  </programme>
  <programme start="20260505070750 +0000" stop="20260505080750 +0000" channel="alwan_sports">
    <title>البطولات الكروية مباشرة</title>
    <desc>نقل مباشر لجميع البطولات الكروية العالمية: دوري الأبطال والدوريات الأوروبية والعالمية.</desc>
  </programme>
  <programme start="20260505080750 +0000" stop="20260505090750 +0000" channel="alwan_sports">
    <title>البطولات الكروية مباشرة</title>
    <desc>نقل مباشر لجميع البطولات الكروية العالمية: دوري الأبطال والدوريات الأوروبية والعالمية.</desc>
  </programme>
  <programme start="20260505090750 +0000" stop="20260505100750 +0000" channel="alwan_sports">
    <title>البطولات الكروية مباشرة</title>
    <desc>نقل مباشر لجميع البطولات الكروية العالمية: دوري الأبطال والدوريات الأوروبية والعالمية.</desc>
  </programme>
  <programme start="20260505100750 +0000" stop="20260505110750 +0000" channel="alwan_sports">
    <title>البطولات الكروية مباشرة</title>
    <desc>نقل مباشر لجميع البطولات الكروية العالمية: دوري الأبطال والدوريات الأوروبية والعالمية.</desc>
  </programme>
  <programme start="20260505110750 +0000" stop="20260505120750 +0000" channel="alwan_sports">
    <title>البطولات الكروية مباشرة</title>
    <desc>نقل مباشر لجميع البطولات الكروية العالمية: دوري الأبطال والدوريات الأوروبية والعالمية.</desc>
  </programme>
  <programme start="20260505120750 +0000" stop="20260505130750 +0000" channel="alwan_sports">
    <title>البطولات الكروية مباشرة</title>
    <desc>نقل مباشر لجميع البطولات الكروية العالمية: دوري الأبطال والدوريات الأوروبية والعالمية.</desc>
  </programme>
  <programme start="20260505130750 +0000" stop="20260505140750 +0000" channel="alwan_sports">
    <title>البطولات الكروية مباشرة</title>
    <desc>نقل مباشر لجميع البطولات الكروية العالمية: دوري الأبطال والدوريات الأوروبية والعالمية.</desc>
  </programme>
  <programme start="20260505140750 +0000" stop="20260505150750 +0000" channel="alwan_sports">
    <title>البطولات الكروية مباشرة</title>
    <desc>نقل مباشر لجميع البطولات الكروية العالمية: دوري الأبطال والدوريات الأوروبية والعالمية.</desc>
  </programme>
  <programme start="20260505150750 +0000" stop="20260505160750 +0000" channel="alwan_sports">
    <title>البطولات الكروية مباشرة</title>
    <desc>نقل مباشر لجميع البطولات الكروية العالمية: دوري الأبطال والدوريات الأوروبية والعالمية.</desc>
  </programme>
  <programme start="20260505160750 +0000" stop="20260505170750 +0000" channel="alwan_sports">
    <title>البطولات الكروية مباشرة</title>
    <desc>نقل مباشر لجميع البطولات الكروية العالمية: دوري الأبطال والدوريات الأوروبية والعالمية.</desc>
  </programme>
  <programme start="20260505170750 +0000" stop="20260505180750 +0000" channel="alwan_sports">
    <title>البطولات الكروية مباشرة</title>
    <desc>نقل مباشر لجميع البطولات الكروية العالمية: دوري الأبطال والدوريات الأوروبية والعالمية.</desc>
  </programme>
  <programme start="20260505180750 +0000" stop="20260505190750 +0000" channel="alwan_sports">
    <title>البطولات الكروية مباشرة</title>
    <desc>نقل مباشر لجميع البطولات الكروية العالمية: دوري الأبطال والدوريات الأوروبية والعالمية.</desc>
  </programme>
  <programme start="20260505190750 +0000" stop="20260505200750 +0000" channel="alwan_sports">
    <title>البطولات الكروية مباشرة</title>
    <desc>نقل مباشر لجميع البطولات الكروية العالمية: دوري الأبطال والدوريات الأوروبية والعالمية.</desc>
  </programme>
  <programme start="20260505200750 +0000" stop="20260505210750 +0000" channel="alwan_sports">
    <title>البطولات الكروية مباشرة</title>
    <desc>نقل مباشر لجميع البطولات الكروية العالمية: دوري الأبطال والدوريات الأوروبية والعالمية.</desc>
  </programme>
  <programme start="20260505210750 +0000" stop="20260505220750 +0000" channel="alwan_sports">
    <title>البطولات الكروية مباشرة</title>
    <desc>نقل مباشر لجميع البطولات الكروية العالمية: دوري الأبطال والدوريات الأوروبية والعالمية.</desc>
  </programme>
  <programme start="20260505220750 +0000" stop="20260505230750 +0000" channel="alwan_sports">
    <title>البطولات الكروية مباشرة</title>
    <desc>نقل مباشر لجميع البطولات الكروية العالمية: دوري الأبطال والدوريات الأوروبية والعالمية.</desc>
  </programme>
  <programme start="20260505230750 +0000" stop="20260506000750 +0000" channel="alwan_sports">
    <title>البطولات الكروية مباشرة</title>
    <desc>نقل مباشر لجميع البطولات الكروية العالمية: دوري الأبطال والدوريات الأوروبية والعالمية.</desc>
  </programme>
  <programme start="20260506000750 +0000" stop="20260506010750 +0000" channel="alwan_sports">
    <title>البطولات الكروية مباشرة</title>
    <desc>نقل مباشر لجميع البطولات الكروية العالمية: دوري الأبطال والدوريات الأوروبية والعالمية.</desc>
  </programme>
  <programme start="20260506010750 +0000" stop="20260506020750 +0000" channel="alwan_sports">
    <title>البطولات الكروية مباشرة</title>
    <desc>نقل مباشر لجميع البطولات الكروية العالمية: دوري الأبطال والدوريات الأوروبية والعالمية.</desc>
  </programme>
  <programme start="20260506020750 +0000" stop="20260506030750 +0000" channel="alwan_sports">
    <title>البطولات الكروية مباشرة</title>
    <desc>نقل مباشر لجميع البطولات الكروية العالمية: دوري الأبطال والدوريات الأوروبية والعالمية.</desc>
  </programme>
  <programme start="20260506030750 +0000" stop="20260506040750 +0000" channel="alwan_sports">
    <title>البطولات الكروية مباشرة</title>
    <desc>نقل مباشر لجميع البطولات الكروية العالمية: دوري الأبطال والدوريات الأوروبية والعالمية.</desc>
  </programme>
  <programme start="20260506040750 +0000" stop="20260506050750 +0000" channel="alwan_sports">
    <title>البطولات الكروية مباشرة</title>
    <desc>نقل مباشر لجميع البطولات الكروية العالمية: دوري الأبطال والدوريات الأوروبية والعالمية.</desc>
  </programme>
  <programme start="20260506050750 +0000" stop="20260506060750 +0000" channel="alwan_sports">
    <title>البطولات الكروية مباشرة</title>
    <desc>نقل مباشر لجميع البطولات الكروية العالمية: دوري الأبطال والدوريات الأوروبية والعالمية.</desc>
  </programme>
  <programme start="20260506060750 +0000" stop="20260506070750 +0000" channel="alwan_sports">
    <title>البطولات الكروية مباشرة</title>
    <desc>نقل مباشر لجميع البطولات الكروية العالمية: دوري الأبطال والدوريات الأوروبية والعالمية.</desc>
  </programme>
  <programme start="20260506070750 +0000" stop="20260506080750 +0000" channel="alwan_sports">
    <title>البطولات الكروية مباشرة</title>
    <desc>نقل مباشر لجميع البطولات الكروية العالمية: دوري الأبطال والدوريات الأوروبية والعالمية.</desc>
  </programme>
  <programme start="20260506080750 +0000" stop="20260506090750 +0000" channel="alwan_sports">
    <title>البطولات الكروية مباشرة</title>
    <desc>نقل مباشر لجميع البطولات الكروية العالمية: دوري الأبطال والدوريات الأوروبية والعالمية.</desc>
  </programme>
  <programme start="20260506090750 +0000" stop="20260506100750 +0000" channel="alwan_sports">
    <title>البطولات الكروية مباشرة</title>
    <desc>نقل مباشر لجميع البطولات الكروية العالمية: دوري الأبطال والدوريات الأوروبية والعالمية.</desc>
  </programme>
  <programme start="20260506100750 +0000" stop="20260506110750 +0000" channel="alwan_sports">
    <title>البطولات الكروية مباشرة</title>
    <desc>نقل مباشر لجميع البطولات الكروية العالمية: دوري الأبطال والدوريات الأوروبية والعالمية.</desc>
  </programme>
  <programme start="20260506110750 +0000" stop="20260506120750 +0000" channel="alwan_sports">
    <title>البطولات الكروية مباشرة</title>
    <desc>نقل مباشر لجميع البطولات الكروية العالمية: دوري الأبطال والدوريات الأوروبية والعالمية.</desc>
  </programme>
  <programme start="20260506120750 +0000" stop="20260506130750 +0000" channel="alwan_sports">
    <title>البطولات الكروية مباشرة</title>
    <desc>نقل مباشر لجميع البطولات الكروية العالمية: دوري الأبطال والدوريات الأوروبية والعالمية.</desc>
  </programme>
  <programme start="20260506130750 +0000" stop="20260506140750 +0000" channel="alwan_sports">
    <title>البطولات الكروية مباشرة</title>
    <desc>نقل مباشر لجميع البطولات الكروية العالمية: دوري الأبطال والدوريات الأوروبية والعالمية.</desc>
  </programme>
  <programme start="20260506140750 +0000" stop="20260506150750 +0000" channel="alwan_sports">
    <title>البطولات الكروية مباشرة</title>
    <desc>نقل مباشر لجميع البطولات الكروية العالمية: دوري الأبطال والدوريات الأوروبية والعالمية.</desc>
  </programme>
  <programme start="20260506150750 +0000" stop="20260506160750 +0000" channel="alwan_sports">
    <title>البطولات الكروية مباشرة</title>
    <desc>نقل مباشر لجميع البطولات الكروية العالمية: دوري الأبطال والدوريات الأوروبية والعالمية.</desc>
  </programme>
  <programme start="20260506160750 +0000" stop="20260506170750 +0000" channel="alwan_sports">
    <title>البطولات الكروية مباشرة</title>
    <desc>نقل مباشر لجميع البطولات الكروية العالمية: دوري الأبطال والدوريات الأوروبية والعالمية.</desc>
  </programme>
  <programme start="20260506170750 +0000" stop="20260506180750 +0000" channel="alwan_sports">
    <title>البطولات الكروية مباشرة</title>
    <desc>نقل مباشر لجميع البطولات الكروية العالمية: دوري الأبطال والدوريات الأوروبية والعالمية.</desc>
  </programme>
  <programme start="20260506180750 +0000" stop="20260506190750 +0000" channel="alwan_sports">
    <title>البطولات الكروية مباشرة</title>
    <desc>نقل مباشر لجميع البطولات الكروية العالمية: دوري الأبطال والدوريات الأوروبية والعالمية.</desc>
  </programme>
  <programme start="20260506190750 +0000" stop="20260506200750 +0000" channel="alwan_sports">
    <title>البطولات الكروية مباشرة</title>
    <desc>نقل مباشر لجميع البطولات الكروية العالمية: دوري الأبطال والدوريات الأوروبية والعالمية.</desc>
  </programme>
  <programme start="20260506200750 +0000" stop="20260506210750 +0000" channel="alwan_sports">
    <title>البطولات الكروية مباشرة</title>
    <desc>نقل مباشر لجميع البطولات الكروية العالمية: دوري الأبطال والدوريات الأوروبية والعالمية.</desc>
  </programme>
  <programme start="20260506210750 +0000" stop="20260506220750 +0000" channel="alwan_sports">
    <title>البطولات الكروية مباشرة</title>
    <desc>نقل مباشر لجميع البطولات الكروية العالمية: دوري الأبطال والدوريات الأوروبية والعالمية.</desc>
  </programme>
  <programme start="20260506220750 +0000" stop="20260506230750 +0000" channel="alwan_sports">
    <title>البطولات الكروية مباشرة</title>
    <desc>نقل مباشر لجميع البطولات الكروية العالمية: دوري الأبطال والدوريات الأوروبية والعالمية.</desc>
  </programme>
  <programme start="20260506230750 +0000" stop="20260507000750 +0000" channel="alwan_sports">
    <title>البطولات الكروية مباشرة</title>
    <desc>نقل مباشر لجميع البطولات الكروية العالمية: دوري الأبطال والدوريات الأوروبية والعالمية.</desc>
  </programme>
  <programme start="20260507000750 +0000" stop="20260507010750 +0000" channel="alwan_sports">
    <title>البطولات الكروية مباشرة</title>
    <desc>نقل مباشر لجميع البطولات الكروية العالمية: دوري الأبطال والدوريات الأوروبية والعالمية.</desc>
  </programme>
  <programme start="20260507010750 +0000" stop="20260507020750 +0000" channel="alwan_sports">
    <title>البطولات الكروية مباشرة</title>
    <desc>نقل مباشر لجميع البطولات الكروية العالمية: دوري الأبطال والدوريات الأوروبية والعالمية.</desc>
  </programme>
  <programme start="20260507020750 +0000" stop="20260507030750 +0000" channel="alwan_sports">
    <title>البطولات الكروية مباشرة</title>
    <desc>نقل مباشر لجميع البطولات الكروية العالمية: دوري الأبطال والدوريات الأوروبية والعالمية.</desc>
  </programme>
  <programme start="20260507030750 +0000" stop="20260507040750 +0000" channel="alwan_sports">
    <title>البطولات الكروية مباشرة</title>
    <desc>نقل مباشر لجميع البطولات الكروية العالمية: دوري الأبطال والدوريات الأوروبية والعالمية.</desc>
  </programme>
  <programme start="20260507040750 +0000" stop="20260507050750 +0000" channel="alwan_sports">
    <title>البطولات الكروية مباشرة</title>
    <desc>نقل مباشر لجميع البطولات الكروية العالمية: دوري الأبطال والدوريات الأوروبية والعالمية.</desc>
  </programme>
  <programme start="20260507050750 +0000" stop="20260507060750 +0000" channel="alwan_sports">
    <title>البطولات الكروية مباشرة</title>
    <desc>نقل مباشر لجميع البطولات الكروية العالمية: دوري الأبطال والدوريات الأوروبية والعالمية.</desc>
  </programme>
  <programme start="20260507060750 +0000" stop="20260507070750 +0000" channel="alwan_sports">
    <title>البطولات الكروية مباشرة</title>
    <desc>نقل مباشر لجميع البطولات الكروية العالمية: دوري الأبطال والدوريات الأوروبية والعالمية.</desc>
  </programme>
  <programme start="20260507070750 +0000" stop="20260507080750 +0000" channel="alwan_sports">
    <title>البطولات الكروية مباشرة</title>
    <desc>نقل مباشر لجميع البطولات الكروية العالمية: دوري الأبطال والدوريات الأوروبية والعالمية.</desc>
  </programme>
  <programme start="20260507080750 +0000" stop="20260507090750 +0000" channel="alwan_sports">
    <title>البطولات الكروية مباشرة</title>
    <desc>نقل مباشر لجميع البطولات الكروية العالمية: دوري الأبطال والدوريات الأوروبية والعالمية.</desc>
  </programme>
  <programme start="20260507090750 +0000" stop="20260507100750 +0000" channel="alwan_sports">
    <title>البطولات الكروية مباشرة</title>
    <desc>نقل مباشر لجميع البطولات الكروية العالمية: دوري الأبطال والدوريات الأوروبية والعالمية.</desc>
  </programme>
  <programme start="20260507100750 +0000" stop="20260507110750 +0000" channel="alwan_sports">
    <title>البطولات الكروية مباشرة</title>
    <desc>نقل مباشر لجميع البطولات الكروية العالمية: دوري الأبطال والدوريات الأوروبية والعالمية.</desc>
  </programme>
  <programme start="20260507110750 +0000" stop="20260507120750 +0000" channel="alwan_sports">
    <title>البطولات الكروية مباشرة</title>
    <desc>نقل مباشر لجميع البطولات الكروية العالمية: دوري الأبطال والدوريات الأوروبية والعالمية.</desc>
  </programme>
  <programme start="20260507120750 +0000" stop="20260507130750 +0000" channel="alwan_sports">
    <title>البطولات الكروية مباشرة</title>
    <desc>نقل مباشر لجميع البطولات الكروية العالمية: دوري الأبطال والدوريات الأوروبية والعالمية.</desc>
  </programme>
  <programme start="20260507130750 +0000" stop="20260507140750 +0000" channel="alwan_sports">
    <title>البطولات الكروية مباشرة</title>
    <desc>نقل مباشر لجميع البطولات الكروية العالمية: دوري الأبطال والدوريات الأوروبية والعالمية.</desc>
  </programme>
  <programme start="20260507140750 +0000" stop="20260507150750 +0000" channel="alwan_sports">
    <title>البطولات الكروية مباشرة</title>
    <desc>نقل مباشر لجميع البطولات الكروية العالمية: دوري الأبطال والدوريات الأوروبية والعالمية.</desc>
  </programme>
  <programme start="20260507150750 +0000" stop="20260507160750 +0000" channel="alwan_sports">
    <title>البطولات الكروية مباشرة</title>
    <desc>نقل مباشر لجميع البطولات الكروية العالمية: دوري الأبطال والدوريات الأوروبية والعالمية.</desc>
  </programme>
  <programme start="20260507160750 +0000" stop="20260507170750 +0000" channel="alwan_sports">
    <title>البطولات الكروية مباشرة</title>
    <desc>نقل مباشر لجميع البطولات الكروية العالمية: دوري الأبطال والدوريات الأوروبية والعالمية.</desc>
  </programme>
  <programme start="20260507170750 +0000" stop="20260507180750 +0000" channel="alwan_sports">
    <title>البطولات الكروية مباشرة</title>
    <desc>نقل مباشر لجميع البطولات الكروية العالمية: دوري الأبطال والدوريات الأوروبية والعالمية.</desc>
  </programme>
  <programme start="20260507180750 +0000" stop="20260507190750 +0000" channel="alwan_sports">
    <title>البطولات الكروية مباشرة</title>
    <desc>نقل مباشر لجميع البطولات الكروية العالمية: دوري الأبطال والدوريات الأوروبية والعالمية.</desc>
  </programme>
  <programme start="20260507190750 +0000" stop="20260507200750 +0000" channel="alwan_sports">
    <title>البطولات الكروية مباشرة</title>
    <desc>نقل مباشر لجميع البطولات الكروية العالمية: دوري الأبطال والدوريات الأوروبية والعالمية.</desc>
  </programme>
  <programme start="20260507200750 +0000" stop="20260507210750 +0000" channel="alwan_sports">
    <title>البطولات الكروية مباشرة</title>
    <desc>نقل مباشر لجميع البطولات الكروية العالمية: دوري الأبطال والدوريات الأوروبية والعالمية.</desc>
  </programme>
  <programme start="20260507210750 +0000" stop="20260507220750 +0000" channel="alwan_sports">
    <title>البطولات الكروية مباشرة</title>
    <desc>نقل مباشر لجميع البطولات الكروية العالمية: دوري الأبطال والدوريات الأوروبية والعالمية.</desc>
  </programme>
  <programme start="20260507220750 +0000" stop="20260507230750 +0000" channel="alwan_sports">
    <title>البطولات الكروية مباشرة</title>
    <desc>نقل مباشر لجميع البطولات الكروية العالمية: دوري الأبطال والدوريات الأوروبية والعالمية.</desc>
  </programme>
  <programme start="20260507230750 +0000" stop="20260508000750 +0000" channel="alwan_sports">
    <title>البطولات الكروية مباشرة</title>
    <desc>نقل مباشر لجميع البطولات الكروية العالمية: دوري الأبطال والدوريات الأوروبية والعالمية.</desc>
  </programme>
  <programme start="20260508000750 +0000" stop="20260508010750 +0000" channel="alwan_sports">
    <title>البطولات الكروية مباشرة</title>
    <desc>نقل مباشر لجميع البطولات الكروية العالمية: دوري الأبطال والدوريات الأوروبية والعالمية.</desc>
  </programme>
  <programme start="20260508010750 +0000" stop="20260508020750 +0000" channel="alwan_sports">
    <title>البطولات الكروية مباشرة</title>
    <desc>نقل مباشر لجميع البطولات الكروية العالمية: دوري الأبطال والدوريات الأوروبية والعالمية.</desc>
  </programme>
  <programme start="20260508020750 +0000" stop="20260508030750 +0000" channel="alwan_sports">
    <title>البطولات الكروية مباشرة</title>
    <desc>نقل مباشر لجميع البطولات الكروية العالمية: دوري الأبطال والدوريات الأوروبية والعالمية.</desc>
  </programme>
  <programme start="20260508030750 +0000" stop="20260508040750 +0000" channel="alwan_sports">
    <title>البطولات الكروية مباشرة</title>
    <desc>نقل مباشر لجميع البطولات الكروية العالمية: دوري الأبطال والدوريات الأوروبية والعالمية.</desc>
  </programme>
</tv>