<?xml version="1.0" encoding="UTF-8"?>
<tv generator-info-name="AlwanSportsEPG">
  <channel id="alwan_sports">
    <display-name>Alwan Sports</display-name>
    <icon src="https://raw.githubusercontent.com/ayoubboukous27/beIN-Sports-EPG-Worldwide/refs/heads/main/Logos/alwan-sports.png"/>
  </channel>
  <programme start="20260428165723 +0000" stop="20260428175723 +0000" channel="alwan_sports">
    <title>البطولات الكروية مباشرة</title>
    <desc>نقل مباشر لجميع البطولات الكروية العالمية: دوري الأبطال والدوريات الأوروبية والعالمية.</desc>
  </programme>
  <programme start="20260428175723 +0000" stop="20260428185723 +0000" channel="alwan_sports">
    <title>البطولات الكروية مباشرة</title>
    <desc>نقل مباشر لجميع البطولات الكروية العالمية: دوري الأبطال والدوريات الأوروبية والعالمية.</desc>
  </programme>
  <programme start="20260428185723 +0000" stop="20260428195723 +0000" channel="alwan_sports">
    <title>البطولات الكروية مباشرة</title>
    <desc>نقل مباشر لجميع البطولات الكروية العالمية: دوري الأبطال والدوريات الأوروبية والعالمية.</desc>
  </programme>
  <programme start="20260428195723 +0000" stop="20260428205723 +0000" channel="alwan_sports">
    <title>البطولات الكروية مباشرة</title>
    <desc>نقل مباشر لجميع البطولات الكروية العالمية: دوري الأبطال والدوريات الأوروبية والعالمية.</desc>
  </programme>
  <programme start="20260428205723 +0000" stop="20260428215723 +0000" channel="alwan_sports">
    <title>البطولات الكروية مباشرة</title>
    <desc>نقل مباشر لجميع البطولات الكروية العالمية: دوري الأبطال والدوريات الأوروبية والعالمية.</desc>
  </programme>
  <programme start="20260428215723 +0000" stop="20260428225723 +0000" channel="alwan_sports">
    <title>البطولات الكروية مباشرة</title>
    <desc>نقل مباشر لجميع البطولات الكروية العالمية: دوري الأبطال والدوريات الأوروبية والعالمية.</desc>
  </programme>
  <programme start="20260428225723 +0000" stop="20260428235723 +0000" channel="alwan_sports">
    <title>البطولات الكروية مباشرة</title>
    <desc>نقل مباشر لجميع البطولات الكروية العالمية: دوري الأبطال والدوريات الأوروبية والعالمية.</desc>
  </programme>
  <programme start="20260428235723 +0000" stop="20260429005723 +0000" channel="alwan_sports">
    <title>البطولات الكروية مباشرة</title>
    <desc>نقل مباشر لجميع البطولات الكروية العالمية: دوري الأبطال والدوريات الأوروبية والعالمية.</desc>
  </programme>
  <programme start="20260429005723 +0000" stop="20260429015723 +0000" channel="alwan_sports">
    <title>البطولات الكروية مباشرة</title>
    <desc>نقل مباشر لجميع البطولات الكروية العالمية: دوري الأبطال والدوريات الأوروبية والعالمية.</desc>
  </programme>
  <programme start="20260429015723 +0000" stop="20260429025723 +0000" channel="alwan_sports">
    <title>البطولات الكروية مباشرة</title>
    <desc>نقل مباشر لجميع البطولات الكروية العالمية: دوري الأبطال والدوريات الأوروبية والعالمية.</desc>
  </programme>
  <programme start="20260429025723 +0000" stop="20260429035723 +0000" channel="alwan_sports">
    <title>البطولات الكروية مباشرة</title>
    <desc>نقل مباشر لجميع البطولات الكروية العالمية: دوري الأبطال والدوريات الأوروبية والعالمية.</desc>
  </programme>
  <programme start="20260429035723 +0000" stop="20260429045723 +0000" channel="alwan_sports">
    <title>البطولات الكروية مباشرة</title>
    <desc>نقل مباشر لجميع البطولات الكروية العالمية: دوري الأبطال والدوريات الأوروبية والعالمية.</desc>
  </programme>
  <programme start="20260429045723 +0000" stop="20260429055723 +0000" channel="alwan_sports">
    <title>البطولات الكروية مباشرة</title>
    <desc>نقل مباشر لجميع البطولات الكروية العالمية: دوري الأبطال والدوريات الأوروبية والعالمية.</desc>
  </programme>
  <programme start="20260429055723 +0000" stop="20260429065723 +0000" channel="alwan_sports">
    <title>البطولات الكروية مباشرة</title>
    <desc>نقل مباشر لجميع البطولات الكروية العالمية: دوري الأبطال والدوريات الأوروبية والعالمية.</desc>
  </programme>
  <programme start="20260429065723 +0000" stop="20260429075723 +0000" channel="alwan_sports">
    <title>البطولات الكروية مباشرة</title>
    <desc>نقل مباشر لجميع البطولات الكروية العالمية: دوري الأبطال والدوريات الأوروبية والعالمية.</desc>
  </programme>
  <programme start="20260429075723 +0000" stop="20260429085723 +0000" channel="alwan_sports">
    <title>البطولات الكروية مباشرة</title>
    <desc>نقل مباشر لجميع البطولات الكروية العالمية: دوري الأبطال والدوريات الأوروبية والعالمية.</desc>
  </programme>
  <programme start="20260429085723 +0000" stop="20260429095723 +0000" channel="alwan_sports">
    <title>البطولات الكروية مباشرة</title>
    <desc>نقل مباشر لجميع البطولات الكروية العالمية: دوري الأبطال والدوريات الأوروبية والعالمية.</desc>
  </programme>
  <programme start="20260429095723 +0000" stop="20260429105723 +0000" channel="alwan_sports">
    <title>البطولات الكروية مباشرة</title>
    <desc>نقل مباشر لجميع البطولات الكروية العالمية: دوري الأبطال والدوريات الأوروبية والعالمية.</desc>
  </programme>
  <programme start="20260429105723 +0000" stop="20260429115723 +0000" channel="alwan_sports">
    <title>البطولات الكروية مباشرة</title>
    <desc>نقل مباشر لجميع البطولات الكروية العالمية: دوري الأبطال والدوريات الأوروبية والعالمية.</desc>
  </programme>
  <programme start="20260429115723 +0000" stop="20260429125723 +0000" channel="alwan_sports">
    <title>البطولات الكروية مباشرة</title>
    <desc>نقل مباشر لجميع البطولات الكروية العالمية: دوري الأبطال والدوريات الأوروبية والعالمية.</desc>
  </programme>
  <programme start="20260429125723 +0000" stop="20260429135723 +0000" channel="alwan_sports">
    <title>البطولات الكروية مباشرة</title>
    <desc>نقل مباشر لجميع البطولات الكروية العالمية: دوري الأبطال والدوريات الأوروبية والعالمية.</desc>
  </programme>
  <programme start="20260429135723 +0000" stop="20260429145723 +0000" channel="alwan_sports">
    <title>البطولات الكروية مباشرة</title>
    <desc>نقل مباشر لجميع البطولات الكروية العالمية: دوري الأبطال والدوريات الأوروبية والعالمية.</desc>
  </programme>
  <programme start="20260429145723 +0000" stop="20260429155723 +0000" channel="alwan_sports">
    <title>البطولات الكروية مباشرة</title>
    <desc>نقل مباشر لجميع البطولات الكروية العالمية: دوري الأبطال والدوريات الأوروبية والعالمية.</desc>
  </programme>
  <programme start="20260429155723 +0000" stop="20260429165723 +0000" channel="alwan_sports">
    <title>البطولات الكروية مباشرة</title>
    <desc>نقل مباشر لجميع البطولات الكروية العالمية: دوري الأبطال والدوريات الأوروبية والعالمية.</desc>
  </programme>
  <programme start="20260429165723 +0000" stop="20260429175723 +0000" channel="alwan_sports">
    <title>البطولات الكروية مباشرة</title>
    <desc>نقل مباشر لجميع البطولات الكروية العالمية: دوري الأبطال والدوريات الأوروبية والعالمية.</desc>
  </programme>
  <programme start="20260429175723 +0000" stop="20260429185723 +0000" channel="alwan_sports">
    <title>البطولات الكروية مباشرة</title>
    <desc>نقل مباشر لجميع البطولات الكروية العالمية: دوري الأبطال والدوريات الأوروبية والعالمية.</desc>
  </programme>
  <programme start="20260429185723 +0000" stop="20260429195723 +0000" channel="alwan_sports">
    <title>البطولات الكروية مباشرة</title>
    <desc>نقل مباشر لجميع البطولات الكروية العالمية: دوري الأبطال والدوريات الأوروبية والعالمية.</desc>
  </programme>
  <programme start="20260429195723 +0000" stop="20260429205723 +0000" channel="alwan_sports">
    <title>البطولات الكروية مباشرة</title>
    <desc>نقل مباشر لجميع البطولات الكروية العالمية: دوري الأبطال والدوريات الأوروبية والعالمية.</desc>
  </programme>
  <programme start="20260429205723 +0000" stop="20260429215723 +0000" channel="alwan_sports">
    <title>البطولات الكروية مباشرة</title>
    <desc>نقل مباشر لجميع البطولات الكروية العالمية: دوري الأبطال والدوريات الأوروبية والعالمية.</desc>
  </programme>
  <programme start="20260429215723 +0000" stop="20260429225723 +0000" channel="alwan_sports">
    <title>البطولات الكروية مباشرة</title>
    <desc>نقل مباشر لجميع البطولات الكروية العالمية: دوري الأبطال والدوريات الأوروبية والعالمية.</desc>
  </programme>
  <programme start="20260429225723 +0000" stop="20260429235723 +0000" channel="alwan_sports">
    <title>البطولات الكروية مباشرة</title>
    <desc>نقل مباشر لجميع البطولات الكروية العالمية: دوري الأبطال والدوريات الأوروبية والعالمية.</desc>
  </programme>
  <programme start="20260429235723 +0000" stop="20260430005723 +0000" channel="alwan_sports">
    <title>البطولات الكروية مباشرة</title>
    <desc>نقل مباشر لجميع البطولات الكروية العالمية: دوري الأبطال والدوريات الأوروبية والعالمية.</desc>
  </programme>
  <programme start="20260430005723 +0000" stop="20260430015723 +0000" channel="alwan_sports">
    <title>البطولات الكروية مباشرة</title>
    <desc>نقل مباشر لجميع البطولات الكروية العالمية: دوري الأبطال والدوريات الأوروبية والعالمية.</desc>
  </programme>
  <programme start="20260430015723 +0000" stop="20260430025723 +0000" channel="alwan_sports">
    <title>البطولات الكروية مباشرة</title>
    <desc>نقل مباشر لجميع البطولات الكروية العالمية: دوري الأبطال والدوريات الأوروبية والعالمية.</desc>
  </programme>
  <programme start="20260430025723 +0000" stop="20260430035723 +0000" channel="alwan_sports">
    <title>البطولات الكروية مباشرة</title>
    <desc>نقل مباشر لجميع البطولات الكروية العالمية: دوري الأبطال والدوريات الأوروبية والعالمية.</desc>
  </programme>
  <programme start="20260430035723 +0000" stop="20260430045723 +0000" channel="alwan_sports">
    <title>البطولات الكروية مباشرة</title>
    <desc>نقل مباشر لجميع البطولات الكروية العالمية: دوري الأبطال والدوريات الأوروبية والعالمية.</desc>
  </programme>
  <programme start="20260430045723 +0000" stop="20260430055723 +0000" channel="alwan_sports">
    <title>البطولات الكروية مباشرة</title>
    <desc>نقل مباشر لجميع البطولات الكروية العالمية: دوري الأبطال والدوريات الأوروبية والعالمية.</desc>
  </programme>
  <programme start="20260430055723 +0000" stop="20260430065723 +0000" channel="alwan_sports">
    <title>البطولات الكروية مباشرة</title>
    <desc>نقل مباشر لجميع البطولات الكروية العالمية: دوري الأبطال والدوريات الأوروبية والعالمية.</desc>
  </programme>
  <programme start="20260430065723 +0000" stop="20260430075723 +0000" channel="alwan_sports">
    <title>البطولات الكروية مباشرة</title>
    <desc>نقل مباشر لجميع البطولات الكروية العالمية: دوري الأبطال والدوريات الأوروبية والعالمية.</desc>
  </programme>
  <programme start="20260430075723 +0000" stop="20260430085723 +0000" channel="alwan_sports">
    <title>البطولات الكروية مباشرة</title>
    <desc>نقل مباشر لجميع البطولات الكروية العالمية: دوري الأبطال والدوريات الأوروبية والعالمية.</desc>
  </programme>
  <programme start="20260430085723 +0000" stop="20260430095723 +0000" channel="alwan_sports">
    <title>البطولات الكروية مباشرة</title>
    <desc>نقل مباشر لجميع البطولات الكروية العالمية: دوري الأبطال والدوريات الأوروبية والعالمية.</desc>
  </programme>
  <programme start="20260430095723 +0000" stop="20260430105723 +0000" channel="alwan_sports">
    <title>البطولات الكروية مباشرة</title>
    <desc>نقل مباشر لجميع البطولات الكروية العالمية: دوري الأبطال والدوريات الأوروبية والعالمية.</desc>
  </programme>
  <programme start="20260430105723 +0000" stop="20260430115723 +0000" channel="alwan_sports">
    <title>البطولات الكروية مباشرة</title>
    <desc>نقل مباشر لجميع البطولات الكروية العالمية: دوري الأبطال والدوريات الأوروبية والعالمية.</desc>
  </programme>
  <programme start="20260430115723 +0000" stop="20260430125723 +0000" channel="alwan_sports">
    <title>البطولات الكروية مباشرة</title>
    <desc>نقل مباشر لجميع البطولات الكروية العالمية: دوري الأبطال والدوريات الأوروبية والعالمية.</desc>
  </programme>
  <programme start="20260430125723 +0000" stop="20260430135723 +0000" channel="alwan_sports">
    <title>البطولات الكروية مباشرة</title>
    <desc>نقل مباشر لجميع البطولات الكروية العالمية: دوري الأبطال والدوريات الأوروبية والعالمية.</desc>
  </programme>
  <programme start="20260430135723 +0000" stop="20260430145723 +0000" channel="alwan_sports">
    <title>البطولات الكروية مباشرة</title>
    <desc>نقل مباشر لجميع البطولات الكروية العالمية: دوري الأبطال والدوريات الأوروبية والعالمية.</desc>
  </programme>
  <programme start="20260430145723 +0000" stop="20260430155723 +0000" channel="alwan_sports">
    <title>البطولات الكروية مباشرة</title>
    <desc>نقل مباشر لجميع البطولات الكروية العالمية: دوري الأبطال والدوريات الأوروبية والعالمية.</desc>
  </programme>
  <programme start="20260430155723 +0000" stop="20260430165723 +0000" channel="alwan_sports">
    <title>البطولات الكروية مباشرة</title>
    <desc>نقل مباشر لجميع البطولات الكروية العالمية: دوري الأبطال والدوريات الأوروبية والعالمية.</desc>
  </programme>
  <programme start="20260430165723 +0000" stop="20260430175723 +0000" channel="alwan_sports">
    <title>البطولات الكروية مباشرة</title>
    <desc>نقل مباشر لجميع البطولات الكروية العالمية: دوري الأبطال والدوريات الأوروبية والعالمية.</desc>
  </programme>
  <programme start="20260430175723 +0000" stop="20260430185723 +0000" channel="alwan_sports">
    <title>البطولات الكروية مباشرة</title>
    <desc>نقل مباشر لجميع البطولات الكروية العالمية: دوري الأبطال والدوريات الأوروبية والعالمية.</desc>
  </programme>
  <programme start="20260430185723 +0000" stop="20260430195723 +0000" channel="alwan_sports">
    <title>البطولات الكروية مباشرة</title>
    <desc>نقل مباشر لجميع البطولات الكروية العالمية: دوري الأبطال والدوريات الأوروبية والعالمية.</desc>
  </programme>
  <programme start="20260430195723 +0000" stop="20260430205723 +0000" channel="alwan_sports">
    <title>البطولات الكروية مباشرة</title>
    <desc>نقل مباشر لجميع البطولات الكروية العالمية: دوري الأبطال والدوريات الأوروبية والعالمية.</desc>
  </programme>
  <programme start="20260430205723 +0000" stop="20260430215723 +0000" channel="alwan_sports">
    <title>البطولات الكروية مباشرة</title>
    <desc>نقل مباشر لجميع البطولات الكروية العالمية: دوري الأبطال والدوريات الأوروبية والعالمية.</desc>
  </programme>
  <programme start="20260430215723 +0000" stop="20260430225723 +0000" channel="alwan_sports">
    <title>البطولات الكروية مباشرة</title>
    <desc>نقل مباشر لجميع البطولات الكروية العالمية: دوري الأبطال والدوريات الأوروبية والعالمية.</desc>
  </programme>
  <programme start="20260430225723 +0000" stop="20260430235723 +0000" channel="alwan_sports">
    <title>البطولات الكروية مباشرة</title>
    <desc>نقل مباشر لجميع البطولات الكروية العالمية: دوري الأبطال والدوريات الأوروبية والعالمية.</desc>
  </programme>
  <programme start="20260430235723 +0000" stop="20260501005723 +0000" channel="alwan_sports">
    <title>البطولات الكروية مباشرة</title>
    <desc>نقل مباشر لجميع البطولات الكروية العالمية: دوري الأبطال والدوريات الأوروبية والعالمية.</desc>
  </programme>
  <programme start="20260501005723 +0000" stop="20260501015723 +0000" channel="alwan_sports">
    <title>البطولات الكروية مباشرة</title>
    <desc>نقل مباشر لجميع البطولات الكروية العالمية: دوري الأبطال والدوريات الأوروبية والعالمية.</desc>
  </programme>
  <programme start="20260501015723 +0000" stop="20260501025723 +0000" channel="alwan_sports">
    <title>البطولات الكروية مباشرة</title>
    <desc>نقل مباشر لجميع البطولات الكروية العالمية: دوري الأبطال والدوريات الأوروبية والعالمية.</desc>
  </programme>
  <programme start="20260501025723 +0000" stop="20260501035723 +0000" channel="alwan_sports">
    <title>البطولات الكروية مباشرة</title>
    <desc>نقل مباشر لجميع البطولات الكروية العالمية: دوري الأبطال والدوريات الأوروبية والعالمية.</desc>
  </programme>
  <programme start="20260501035723 +0000" stop="20260501045723 +0000" channel="alwan_sports">
    <title>البطولات الكروية مباشرة</title>
    <desc>نقل مباشر لجميع البطولات الكروية العالمية: دوري الأبطال والدوريات الأوروبية والعالمية.</desc>
  </programme>
  <programme start="20260501045723 +0000" stop="20260501055723 +0000" channel="alwan_sports">
    <title>البطولات الكروية مباشرة</title>
    <desc>نقل مباشر لجميع البطولات الكروية العالمية: دوري الأبطال والدوريات الأوروبية والعالمية.</desc>
  </programme>
  <programme start="20260501055723 +0000" stop="20260501065723 +0000" channel="alwan_sports">
    <title>البطولات الكروية مباشرة</title>
    <desc>نقل مباشر لجميع البطولات الكروية العالمية: دوري الأبطال والدوريات الأوروبية والعالمية.</desc>
  </programme>
  <programme start="20260501065723 +0000" stop="20260501075723 +0000" channel="alwan_sports">
    <title>البطولات الكروية مباشرة</title>
    <desc>نقل مباشر لجميع البطولات الكروية العالمية: دوري الأبطال والدوريات الأوروبية والعالمية.</desc>
  </programme>
  <programme start="20260501075723 +0000" stop="20260501085723 +0000" channel="alwan_sports">
    <title>البطولات الكروية مباشرة</title>
    <desc>نقل مباشر لجميع البطولات الكروية العالمية: دوري الأبطال والدوريات الأوروبية والعالمية.</desc>
  </programme>
  <programme start="20260501085723 +0000" stop="20260501095723 +0000" channel="alwan_sports">
    <title>البطولات الكروية مباشرة</title>
    <desc>نقل مباشر لجميع البطولات الكروية العالمية: دوري الأبطال والدوريات الأوروبية والعالمية.</desc>
  </programme>
  <programme start="20260501095723 +0000" stop="20260501105723 +0000" channel="alwan_sports">
    <title>البطولات الكروية مباشرة</title>
    <desc>نقل مباشر لجميع البطولات الكروية العالمية: دوري الأبطال والدوريات الأوروبية والعالمية.</desc>
  </programme>
  <programme start="20260501105723 +0000" stop="20260501115723 +0000" channel="alwan_sports">
    <title>البطولات الكروية مباشرة</title>
    <desc>نقل مباشر لجميع البطولات الكروية العالمية: دوري الأبطال والدوريات الأوروبية والعالمية.</desc>
  </programme>
  <programme start="20260501115723 +0000" stop="20260501125723 +0000" channel="alwan_sports">
    <title>البطولات الكروية مباشرة</title>
    <desc>نقل مباشر لجميع البطولات الكروية العالمية: دوري الأبطال والدوريات الأوروبية والعالمية.</desc>
  </programme>
  <programme start="20260501125723 +0000" stop="20260501135723 +0000" channel="alwan_sports">
    <title>البطولات الكروية مباشرة</title>
    <desc>نقل مباشر لجميع البطولات الكروية العالمية: دوري الأبطال والدوريات الأوروبية والعالمية.</desc>
  </programme>
  <programme start="20260501135723 +0000" stop="20260501145723 +0000" channel="alwan_sports">
    <title>البطولات الكروية مباشرة</title>
    <desc>نقل مباشر لجميع البطولات الكروية العالمية: دوري الأبطال والدوريات الأوروبية والعالمية.</desc>
  </programme>
  <programme start="20260501145723 +0000" stop="20260501155723 +0000" channel="alwan_sports">
    <title>البطولات الكروية مباشرة</title>
    <desc>نقل مباشر لجميع البطولات الكروية العالمية: دوري الأبطال والدوريات الأوروبية والعالمية.</desc>
  </programme>
  <programme start="20260501155723 +0000" stop="20260501165723 +0000" channel="alwan_sports">
    <title>البطولات الكروية مباشرة</title>
    <desc>نقل مباشر لجميع البطولات الكروية العالمية: دوري الأبطال والدوريات الأوروبية والعالمية.</desc>
  </programme>
  <programme start="20260501165723 +0000" stop="20260501175723 +0000" channel="alwan_sports">
    <title>البطولات الكروية مباشرة</title>
    <desc>نقل مباشر لجميع البطولات الكروية العالمية: دوري الأبطال والدوريات الأوروبية والعالمية.</desc>
  </programme>
  <programme start="20260501175723 +0000" stop="20260501185723 +0000" channel="alwan_sports">
    <title>البطولات الكروية مباشرة</title>
    <desc>نقل مباشر لجميع البطولات الكروية العالمية: دوري الأبطال والدوريات الأوروبية والعالمية.</desc>
  </programme>
  <programme start="20260501185723 +0000" stop="20260501195723 +0000" channel="alwan_sports">
    <title>البطولات الكروية مباشرة</title>
    <desc>نقل مباشر لجميع البطولات الكروية العالمية: دوري الأبطال والدوريات الأوروبية والعالمية.</desc>
  </programme>
  <programme start="20260501195723 +0000" stop="20260501205723 +0000" channel="alwan_sports">
    <title>البطولات الكروية مباشرة</title>
    <desc>نقل مباشر لجميع البطولات الكروية العالمية: دوري الأبطال والدوريات الأوروبية والعالمية.</desc>
  </programme>
  <programme start="20260501205723 +0000" stop="20260501215723 +0000" channel="alwan_sports">
    <title>البطولات الكروية مباشرة</title>
    <desc>نقل مباشر لجميع البطولات الكروية العالمية: دوري الأبطال والدوريات الأوروبية والعالمية.</desc>
  </programme>
  <programme start="20260501215723 +0000" stop="20260501225723 +0000" channel="alwan_sports">
    <title>البطولات الكروية مباشرة</title>
    <desc>نقل مباشر لجميع البطولات الكروية العالمية: دوري الأبطال والدوريات الأوروبية والعالمية.</desc>
  </programme>
  <programme start="20260501225723 +0000" stop="20260501235723 +0000" channel="alwan_sports">
    <title>البطولات الكروية مباشرة</title>
    <desc>نقل مباشر لجميع البطولات الكروية العالمية: دوري الأبطال والدوريات الأوروبية والعالمية.</desc>
  </programme>
  <programme start="20260501235723 +0000" stop="20260502005723 +0000" channel="alwan_sports">
    <title>البطولات الكروية مباشرة</title>
    <desc>نقل مباشر لجميع البطولات الكروية العالمية: دوري الأبطال والدوريات الأوروبية والعالمية.</desc>
  </programme>
  <programme start="20260502005723 +0000" stop="20260502015723 +0000" channel="alwan_sports">
    <title>البطولات الكروية مباشرة</title>
    <desc>نقل مباشر لجميع البطولات الكروية العالمية: دوري الأبطال والدوريات الأوروبية والعالمية.</desc>
  </programme>
  <programme start="20260502015723 +0000" stop="20260502025723 +0000" channel="alwan_sports">
    <title>البطولات الكروية مباشرة</title>
    <desc>نقل مباشر لجميع البطولات الكروية العالمية: دوري الأبطال والدوريات الأوروبية والعالمية.</desc>
  </programme>
  <programme start="20260502025723 +0000" stop="20260502035723 +0000" channel="alwan_sports">
    <title>البطولات الكروية مباشرة</title>
    <desc>نقل مباشر لجميع البطولات الكروية العالمية: دوري الأبطال والدوريات الأوروبية والعالمية.</desc>
  </programme>
  <programme start="20260502035723 +0000" stop="20260502045723 +0000" channel="alwan_sports">
    <title>البطولات الكروية مباشرة</title>
    <desc>نقل مباشر لجميع البطولات الكروية العالمية: دوري الأبطال والدوريات الأوروبية والعالمية.</desc>
  </programme>
  <programme start="20260502045723 +0000" stop="20260502055723 +0000" channel="alwan_sports">
    <title>البطولات الكروية مباشرة</title>
    <desc>نقل مباشر لجميع البطولات الكروية العالمية: دوري الأبطال والدوريات الأوروبية والعالمية.</desc>
  </programme>
  <programme start="20260502055723 +0000" stop="20260502065723 +0000" channel="alwan_sports">
    <title>البطولات الكروية مباشرة</title>
    <desc>نقل مباشر لجميع البطولات الكروية العالمية: دوري الأبطال والدوريات الأوروبية والعالمية.</desc>
  </programme>
  <programme start="20260502065723 +0000" stop="20260502075723 +0000" channel="alwan_sports">
    <title>البطولات الكروية مباشرة</title>
    <desc>نقل مباشر لجميع البطولات الكروية العالمية: دوري الأبطال والدوريات الأوروبية والعالمية.</desc>
  </programme>
  <programme start="20260502075723 +0000" stop="20260502085723 +0000" channel="alwan_sports">
    <title>البطولات الكروية مباشرة</title>
    <desc>نقل مباشر لجميع البطولات الكروية العالمية: دوري الأبطال والدوريات الأوروبية والعالمية.</desc>
  </programme>
  <programme start="20260502085723 +0000" stop="20260502095723 +0000" channel="alwan_sports">
    <title>البطولات الكروية مباشرة</title>
    <desc>نقل مباشر لجميع البطولات الكروية العالمية: دوري الأبطال والدوريات الأوروبية والعالمية.</desc>
  </programme>
  <programme start="20260502095723 +0000" stop="20260502105723 +0000" channel="alwan_sports">
    <title>البطولات الكروية مباشرة</title>
    <desc>نقل مباشر لجميع البطولات الكروية العالمية: دوري الأبطال والدوريات الأوروبية والعالمية.</desc>
  </programme>
  <programme start="20260502105723 +0000" stop="20260502115723 +0000" channel="alwan_sports">
    <title>البطولات الكروية مباشرة</title>
    <desc>نقل مباشر لجميع البطولات الكروية العالمية: دوري الأبطال والدوريات الأوروبية والعالمية.</desc>
  </programme>
  <programme start="20260502115723 +0000" stop="20260502125723 +0000" channel="alwan_sports">
    <title>البطولات الكروية مباشرة</title>
    <desc>نقل مباشر لجميع البطولات الكروية العالمية: دوري الأبطال والدوريات الأوروبية والعالمية.</desc>
  </programme>
  <programme start="20260502125723 +0000" stop="20260502135723 +0000" channel="alwan_sports">
    <title>البطولات الكروية مباشرة</title>
    <desc>نقل مباشر لجميع البطولات الكروية العالمية: دوري الأبطال والدوريات الأوروبية والعالمية.</desc>
  </programme>
  <programme start="20260502135723 +0000" stop="20260502145723 +0000" channel="alwan_sports">
    <title>البطولات الكروية مباشرة</title>
    <desc>نقل مباشر لجميع البطولات الكروية العالمية: دوري الأبطال والدوريات الأوروبية والعالمية.</desc>
  </programme>
  <programme start="20260502145723 +0000" stop="20260502155723 +0000" channel="alwan_sports">
    <title>البطولات الكروية مباشرة</title>
    <desc>نقل مباشر لجميع البطولات الكروية العالمية: دوري الأبطال والدوريات الأوروبية والعالمية.</desc>
  </programme>
  <programme start="20260502155723 +0000" stop="20260502165723 +0000" channel="alwan_sports">
    <title>البطولات الكروية مباشرة</title>
    <desc>نقل مباشر لجميع البطولات الكروية العالمية: دوري الأبطال والدوريات الأوروبية والعالمية.</desc>
  </programme>
  <programme start="20260502165723 +0000" stop="20260502175723 +0000" channel="alwan_sports">
    <title>البطولات الكروية مباشرة</title>
    <desc>نقل مباشر لجميع البطولات الكروية العالمية: دوري الأبطال والدوريات الأوروبية والعالمية.</desc>
  </programme>
  <programme start="20260502175723 +0000" stop="20260502185723 +0000" channel="alwan_sports">
    <title>البطولات الكروية مباشرة</title>
    <desc>نقل مباشر لجميع البطولات الكروية العالمية: دوري الأبطال والدوريات الأوروبية والعالمية.</desc>
  </programme>
  <programme start="20260502185723 +0000" stop="20260502195723 +0000" channel="alwan_sports">
    <title>البطولات الكروية مباشرة</title>
    <desc>نقل مباشر لجميع البطولات الكروية العالمية: دوري الأبطال والدوريات الأوروبية والعالمية.</desc>
  </programme>
  <programme start="20260502195723 +0000" stop="20260502205723 +0000" channel="alwan_sports">
    <title>البطولات الكروية مباشرة</title>
    <desc>نقل مباشر لجميع البطولات الكروية العالمية: دوري الأبطال والدوريات الأوروبية والعالمية.</desc>
  </programme>
  <programme start="20260502205723 +0000" stop="20260502215723 +0000" channel="alwan_sports">
    <title>البطولات الكروية مباشرة</title>
    <desc>نقل مباشر لجميع البطولات الكروية العالمية: دوري الأبطال والدوريات الأوروبية والعالمية.</desc>
  </programme>
  <programme start="20260502215723 +0000" stop="20260502225723 +0000" channel="alwan_sports">
    <title>البطولات الكروية مباشرة</title>
    <desc>نقل مباشر لجميع البطولات الكروية العالمية: دوري الأبطال والدوريات الأوروبية والعالمية.</desc>
  </programme>
  <programme start="20260502225723 +0000" stop="20260502235723 +0000" channel="alwan_sports">
    <title>البطولات الكروية مباشرة</title>
    <desc>نقل مباشر لجميع البطولات الكروية العالمية: دوري الأبطال والدوريات الأوروبية والعالمية.</desc>
  </programme>
  <programme start="20260502235723 +0000" stop="20260503005723 +0000" channel="alwan_sports">
    <title>البطولات الكروية مباشرة</title>
    <desc>نقل مباشر لجميع البطولات الكروية العالمية: دوري الأبطال والدوريات الأوروبية والعالمية.</desc>
  </programme>
  <programme start="20260503005723 +0000" stop="20260503015723 +0000" channel="alwan_sports">
    <title>البطولات الكروية مباشرة</title>
    <desc>نقل مباشر لجميع البطولات الكروية العالمية: دوري الأبطال والدوريات الأوروبية والعالمية.</desc>
  </programme>
  <programme start="20260503015723 +0000" stop="20260503025723 +0000" channel="alwan_sports">
    <title>البطولات الكروية مباشرة</title>
    <desc>نقل مباشر لجميع البطولات الكروية العالمية: دوري الأبطال والدوريات الأوروبية والعالمية.</desc>
  </programme>
  <programme start="20260503025723 +0000" stop="20260503035723 +0000" channel="alwan_sports">
    <title>البطولات الكروية مباشرة</title>
    <desc>نقل مباشر لجميع البطولات الكروية العالمية: دوري الأبطال والدوريات الأوروبية والعالمية.</desc>
  </programme>
  <programme start="20260503035723 +0000" stop="20260503045723 +0000" channel="alwan_sports">
    <title>البطولات الكروية مباشرة</title>
    <desc>نقل مباشر لجميع البطولات الكروية العالمية: دوري الأبطال والدوريات الأوروبية والعالمية.</desc>
  </programme>
  <programme start="20260503045723 +0000" stop="20260503055723 +0000" channel="alwan_sports">
    <title>البطولات الكروية مباشرة</title>
    <desc>نقل مباشر لجميع البطولات الكروية العالمية: دوري الأبطال والدوريات الأوروبية والعالمية.</desc>
  </programme>
  <programme start="20260503055723 +0000" stop="20260503065723 +0000" channel="alwan_sports">
    <title>البطولات الكروية مباشرة</title>
    <desc>نقل مباشر لجميع البطولات الكروية العالمية: دوري الأبطال والدوريات الأوروبية والعالمية.</desc>
  </programme>
  <programme start="20260503065723 +0000" stop="20260503075723 +0000" channel="alwan_sports">
    <title>البطولات الكروية مباشرة</title>
    <desc>نقل مباشر لجميع البطولات الكروية العالمية: دوري الأبطال والدوريات الأوروبية والعالمية.</desc>
  </programme>
  <programme start="20260503075723 +0000" stop="20260503085723 +0000" channel="alwan_sports">
    <title>البطولات الكروية مباشرة</title>
    <desc>نقل مباشر لجميع البطولات الكروية العالمية: دوري الأبطال والدوريات الأوروبية والعالمية.</desc>
  </programme>
  <programme start="20260503085723 +0000" stop="20260503095723 +0000" channel="alwan_sports">
    <title>البطولات الكروية مباشرة</title>
    <desc>نقل مباشر لجميع البطولات الكروية العالمية: دوري الأبطال والدوريات الأوروبية والعالمية.</desc>
  </programme>
  <programme start="20260503095723 +0000" stop="20260503105723 +0000" channel="alwan_sports">
    <title>البطولات الكروية مباشرة</title>
    <desc>نقل مباشر لجميع البطولات الكروية العالمية: دوري الأبطال والدوريات الأوروبية والعالمية.</desc>
  </programme>
  <programme start="20260503105723 +0000" stop="20260503115723 +0000" channel="alwan_sports">
    <title>البطولات الكروية مباشرة</title>
    <desc>نقل مباشر لجميع البطولات الكروية العالمية: دوري الأبطال والدوريات الأوروبية والعالمية.</desc>
  </programme>
  <programme start="20260503115723 +0000" stop="20260503125723 +0000" channel="alwan_sports">
    <title>البطولات الكروية مباشرة</title>
    <desc>نقل مباشر لجميع البطولات الكروية العالمية: دوري الأبطال والدوريات الأوروبية والعالمية.</desc>
  </programme>
  <programme start="20260503125723 +0000" stop="20260503135723 +0000" channel="alwan_sports">
    <title>البطولات الكروية مباشرة</title>
    <desc>نقل مباشر لجميع البطولات الكروية العالمية: دوري الأبطال والدوريات الأوروبية والعالمية.</desc>
  </programme>
  <programme start="20260503135723 +0000" stop="20260503145723 +0000" channel="alwan_sports">
    <title>البطولات الكروية مباشرة</title>
    <desc>نقل مباشر لجميع البطولات الكروية العالمية: دوري الأبطال والدوريات الأوروبية والعالمية.</desc>
  </programme>
  <programme start="20260503145723 +0000" stop="20260503155723 +0000" channel="alwan_sports">
    <title>البطولات الكروية مباشرة</title>
    <desc>نقل مباشر لجميع البطولات الكروية العالمية: دوري الأبطال والدوريات الأوروبية والعالمية.</desc>
  </programme>
  <programme start="20260503155723 +0000" stop="20260503165723 +0000" channel="alwan_sports">
    <title>البطولات الكروية مباشرة</title>
    <desc>نقل مباشر لجميع البطولات الكروية العالمية: دوري الأبطال والدوريات الأوروبية والعالمية.</desc>
  </programme>
  <programme start="20260503165723 +0000" stop="20260503175723 +0000" channel="alwan_sports">
    <title>البطولات الكروية مباشرة</title>
    <desc>نقل مباشر لجميع البطولات الكروية العالمية: دوري الأبطال والدوريات الأوروبية والعالمية.</desc>
  </programme>
  <programme start="20260503175723 +0000" stop="20260503185723 +0000" channel="alwan_sports">
    <title>البطولات الكروية مباشرة</title>
    <desc>نقل مباشر لجميع البطولات الكروية العالمية: دوري الأبطال والدوريات الأوروبية والعالمية.</desc>
  </programme>
  <programme start="20260503185723 +0000" stop="20260503195723 +0000" channel="alwan_sports">
    <title>البطولات الكروية مباشرة</title>
    <desc>نقل مباشر لجميع البطولات الكروية العالمية: دوري الأبطال والدوريات الأوروبية والعالمية.</desc>
  </programme>
  <programme start="20260503195723 +0000" stop="20260503205723 +0000" channel="alwan_sports">
    <title>البطولات الكروية مباشرة</title>
    <desc>نقل مباشر لجميع البطولات الكروية العالمية: دوري الأبطال والدوريات الأوروبية والعالمية.</desc>
  </programme>
  <programme start="20260503205723 +0000" stop="20260503215723 +0000" channel="alwan_sports">
    <title>البطولات الكروية مباشرة</title>
    <desc>نقل مباشر لجميع البطولات الكروية العالمية: دوري الأبطال والدوريات الأوروبية والعالمية.</desc>
  </programme>
  <programme start="20260503215723 +0000" stop="20260503225723 +0000" channel="alwan_sports">
    <title>البطولات الكروية مباشرة</title>
    <desc>نقل مباشر لجميع البطولات الكروية العالمية: دوري الأبطال والدوريات الأوروبية والعالمية.</desc>
  </programme>
  <programme start="20260503225723 +0000" stop="20260503235723 +0000" channel="alwan_sports">
    <title>البطولات الكروية مباشرة</title>
    <desc>نقل مباشر لجميع البطولات الكروية العالمية: دوري الأبطال والدوريات الأوروبية والعالمية.</desc>
  </programme>
  <programme start="20260503235723 +0000" stop="20260504005723 +0000" channel="alwan_sports">
    <title>البطولات الكروية مباشرة</title>
    <desc>نقل مباشر لجميع البطولات الكروية العالمية: دوري الأبطال والدوريات الأوروبية والعالمية.</desc>
  </programme>
  <programme start="20260504005723 +0000" stop="20260504015723 +0000" channel="alwan_sports">
    <title>البطولات الكروية مباشرة</title>
    <desc>نقل مباشر لجميع البطولات الكروية العالمية: دوري الأبطال والدوريات الأوروبية والعالمية.</desc>
  </programme>
  <programme start="20260504015723 +0000" stop="20260504025723 +0000" channel="alwan_sports">
    <title>البطولات الكروية مباشرة</title>
    <desc>نقل مباشر لجميع البطولات الكروية العالمية: دوري الأبطال والدوريات الأوروبية والعالمية.</desc>
  </programme>
  <programme start="20260504025723 +0000" stop="20260504035723 +0000" channel="alwan_sports">
    <title>البطولات الكروية مباشرة</title>
    <desc>نقل مباشر لجميع البطولات الكروية العالمية: دوري الأبطال والدوريات الأوروبية والعالمية.</desc>
  </programme>
  <programme start="20260504035723 +0000" stop="20260504045723 +0000" channel="alwan_sports">
    <title>البطولات الكروية مباشرة</title>
    <desc>نقل مباشر لجميع البطولات الكروية العالمية: دوري الأبطال والدوريات الأوروبية والعالمية.</desc>
  </programme>
  <programme start="20260504045723 +0000" stop="20260504055723 +0000" channel="alwan_sports">
    <title>البطولات الكروية مباشرة</title>
    <desc>نقل مباشر لجميع البطولات الكروية العالمية: دوري الأبطال والدوريات الأوروبية والعالمية.</desc>
  </programme>
  <programme start="20260504055723 +0000" stop="20260504065723 +0000" channel="alwan_sports">
    <title>البطولات الكروية مباشرة</title>
    <desc>نقل مباشر لجميع البطولات الكروية العالمية: دوري الأبطال والدوريات الأوروبية والعالمية.</desc>
  </programme>
  <programme start="20260504065723 +0000" stop="20260504075723 +0000" channel="alwan_sports">
    <title>البطولات الكروية مباشرة</title>
    <desc>نقل مباشر لجميع البطولات الكروية العالمية: دوري الأبطال والدوريات الأوروبية والعالمية.</desc>
  </programme>
  <programme start="20260504075723 +0000" stop="20260504085723 +0000" channel="alwan_sports">
    <title>البطولات الكروية مباشرة</title>
    <desc>نقل مباشر لجميع البطولات الكروية العالمية: دوري الأبطال والدوريات الأوروبية والعالمية.</desc>
  </programme>
  <programme start="20260504085723 +0000" stop="20260504095723 +0000" channel="alwan_sports">
    <title>البطولات الكروية مباشرة</title>
    <desc>نقل مباشر لجميع البطولات الكروية العالمية: دوري الأبطال والدوريات الأوروبية والعالمية.</desc>
  </programme>
  <programme start="20260504095723 +0000" stop="20260504105723 +0000" channel="alwan_sports">
    <title>البطولات الكروية مباشرة</title>
    <desc>نقل مباشر لجميع البطولات الكروية العالمية: دوري الأبطال والدوريات الأوروبية والعالمية.</desc>
  </programme>
  <programme start="20260504105723 +0000" stop="20260504115723 +0000" channel="alwan_sports">
    <title>البطولات الكروية مباشرة</title>
    <desc>نقل مباشر لجميع البطولات الكروية العالمية: دوري الأبطال والدوريات الأوروبية والعالمية.</desc>
  </programme>
  <programme start="20260504115723 +0000" stop="20260504125723 +0000" channel="alwan_sports">
    <title>البطولات الكروية مباشرة</title>
    <desc>نقل مباشر لجميع البطولات الكروية العالمية: دوري الأبطال والدوريات الأوروبية والعالمية.</desc>
  </programme>
  <programme start="20260504125723 +0000" stop="20260504135723 +0000" channel="alwan_sports">
    <title>البطولات الكروية مباشرة</title>
    <desc>نقل مباشر لجميع البطولات الكروية العالمية: دوري الأبطال والدوريات الأوروبية والعالمية.</desc>
  </programme>
  <programme start="20260504135723 +0000" stop="20260504145723 +0000" channel="alwan_sports">
    <title>البطولات الكروية مباشرة</title>
    <desc>نقل مباشر لجميع البطولات الكروية العالمية: دوري الأبطال والدوريات الأوروبية والعالمية.</desc>
  </programme>
  <programme start="20260504145723 +0000" stop="20260504155723 +0000" channel="alwan_sports">
    <title>البطولات الكروية مباشرة</title>
    <desc>نقل مباشر لجميع البطولات الكروية العالمية: دوري الأبطال والدوريات الأوروبية والعالمية.</desc>
  </programme>
  <programme start="20260504155723 +0000" stop="20260504165723 +0000" channel="alwan_sports">
    <title>البطولات الكروية مباشرة</title>
    <desc>نقل مباشر لجميع البطولات الكروية العالمية: دوري الأبطال والدوريات الأوروبية والعالمية.</desc>
  </programme>
  <programme start="20260504165723 +0000" stop="20260504175723 +0000" channel="alwan_sports">
    <title>البطولات الكروية مباشرة</title>
    <desc>نقل مباشر لجميع البطولات الكروية العالمية: دوري الأبطال والدوريات الأوروبية والعالمية.</desc>
  </programme>
  <programme start="20260504175723 +0000" stop="20260504185723 +0000" channel="alwan_sports">
    <title>البطولات الكروية مباشرة</title>
    <desc>نقل مباشر لجميع البطولات الكروية العالمية: دوري الأبطال والدوريات الأوروبية والعالمية.</desc>
  </programme>
  <programme start="20260504185723 +0000" stop="20260504195723 +0000" channel="alwan_sports">
    <title>البطولات الكروية مباشرة</title>
    <desc>نقل مباشر لجميع البطولات الكروية العالمية: دوري الأبطال والدوريات الأوروبية والعالمية.</desc>
  </programme>
  <programme start="20260504195723 +0000" stop="20260504205723 +0000" channel="alwan_sports">
    <title>البطولات الكروية مباشرة</title>
    <desc>نقل مباشر لجميع البطولات الكروية العالمية: دوري الأبطال والدوريات الأوروبية والعالمية.</desc>
  </programme>
  <programme start="20260504205723 +0000" stop="20260504215723 +0000" channel="alwan_sports">
    <title>البطولات الكروية مباشرة</title>
    <desc>نقل مباشر لجميع البطولات الكروية العالمية: دوري الأبطال والدوريات الأوروبية والعالمية.</desc>
  </programme>
  <programme start="20260504215723 +0000" stop="20260504225723 +0000" channel="alwan_sports">
    <title>البطولات الكروية مباشرة</title>
    <desc>نقل مباشر لجميع البطولات الكروية العالمية: دوري الأبطال والدوريات الأوروبية والعالمية.</desc>
  </programme>
  <programme start="20260504225723 +0000" stop="20260504235723 +0000" channel="alwan_sports">
    <title>البطولات الكروية مباشرة</title>
    <desc>نقل مباشر لجميع البطولات الكروية العالمية: دوري الأبطال والدوريات الأوروبية والعالمية.</desc>
  </programme>
  <programme start="20260504235723 +0000" stop="20260505005723 +0000" channel="alwan_sports">
    <title>البطولات الكروية مباشرة</title>
    <desc>نقل مباشر لجميع البطولات الكروية العالمية: دوري الأبطال والدوريات الأوروبية والعالمية.</desc>
  </programme>
  <programme start="20260505005723 +0000" stop="20260505015723 +0000" channel="alwan_sports">
    <title>البطولات الكروية مباشرة</title>
    <desc>نقل مباشر لجميع البطولات الكروية العالمية: دوري الأبطال والدوريات الأوروبية والعالمية.</desc>
  </programme>
  <programme start="20260505015723 +0000" stop="20260505025723 +0000" channel="alwan_sports">
    <title>البطولات الكروية مباشرة</title>
    <desc>نقل مباشر لجميع البطولات الكروية العالمية: دوري الأبطال والدوريات الأوروبية والعالمية.</desc>
  </programme>
  <programme start="20260505025723 +0000" stop="20260505035723 +0000" channel="alwan_sports">
    <title>البطولات الكروية مباشرة</title>
    <desc>نقل مباشر لجميع البطولات الكروية العالمية: دوري الأبطال والدوريات الأوروبية والعالمية.</desc>
  </programme>
  <programme start="20260505035723 +0000" stop="20260505045723 +0000" channel="alwan_sports">
    <title>البطولات الكروية مباشرة</title>
    <desc>نقل مباشر لجميع البطولات الكروية العالمية: دوري الأبطال والدوريات الأوروبية والعالمية.</desc>
  </programme>
  <programme start="20260505045723 +0000" stop="20260505055723 +0000" channel="alwan_sports">
    <title>البطولات الكروية مباشرة</title>
    <desc>نقل مباشر لجميع البطولات الكروية العالمية: دوري الأبطال والدوريات الأوروبية والعالمية.</desc>
  </programme>
  <programme start="20260505055723 +0000" stop="20260505065723 +0000" channel="alwan_sports">
    <title>البطولات الكروية مباشرة</title>
    <desc>نقل مباشر لجميع البطولات الكروية العالمية: دوري الأبطال والدوريات الأوروبية والعالمية.</desc>
  </programme>
  <programme start="20260505065723 +0000" stop="20260505075723 +0000" channel="alwan_sports">
    <title>البطولات الكروية مباشرة</title>
    <desc>نقل مباشر لجميع البطولات الكروية العالمية: دوري الأبطال والدوريات الأوروبية والعالمية.</desc>
  </programme>
  <programme start="20260505075723 +0000" stop="20260505085723 +0000" channel="alwan_sports">
    <title>البطولات الكروية مباشرة</title>
    <desc>نقل مباشر لجميع البطولات الكروية العالمية: دوري الأبطال والدوريات الأوروبية والعالمية.</desc>
  </programme>
  <programme start="20260505085723 +0000" stop="20260505095723 +0000" channel="alwan_sports">
    <title>البطولات الكروية مباشرة</title>
    <desc>نقل مباشر لجميع البطولات الكروية العالمية: دوري الأبطال والدوريات الأوروبية والعالمية.</desc>
  </programme>
  <programme start="20260505095723 +0000" stop="20260505105723 +0000" channel="alwan_sports">
    <title>البطولات الكروية مباشرة</title>
    <desc>نقل مباشر لجميع البطولات الكروية العالمية: دوري الأبطال والدوريات الأوروبية والعالمية.</desc>
  </programme>
  <programme start="20260505105723 +0000" stop="20260505115723 +0000" channel="alwan_sports">
    <title>البطولات الكروية مباشرة</title>
    <desc>نقل مباشر لجميع البطولات الكروية العالمية: دوري الأبطال والدوريات الأوروبية والعالمية.</desc>
  </programme>
  <programme start="20260505115723 +0000" stop="20260505125723 +0000" channel="alwan_sports">
    <title>البطولات الكروية مباشرة</title>
    <desc>نقل مباشر لجميع البطولات الكروية العالمية: دوري الأبطال والدوريات الأوروبية والعالمية.</desc>
  </programme>
  <programme start="20260505125723 +0000" stop="20260505135723 +0000" channel="alwan_sports">
    <title>البطولات الكروية مباشرة</title>
    <desc>نقل مباشر لجميع البطولات الكروية العالمية: دوري الأبطال والدوريات الأوروبية والعالمية.</desc>
  </programme>
  <programme start="20260505135723 +0000" stop="20260505145723 +0000" channel="alwan_sports">
    <title>البطولات الكروية مباشرة</title>
    <desc>نقل مباشر لجميع البطولات الكروية العالمية: دوري الأبطال والدوريات الأوروبية والعالمية.</desc>
  </programme>
  <programme start="20260505145723 +0000" stop="20260505155723 +0000" channel="alwan_sports">
    <title>البطولات الكروية مباشرة</title>
    <desc>نقل مباشر لجميع البطولات الكروية العالمية: دوري الأبطال والدوريات الأوروبية والعالمية.</desc>
  </programme>
  <programme start="20260505155723 +0000" stop="20260505165723 +0000" channel="alwan_sports">
    <title>البطولات الكروية مباشرة</title>
    <desc>نقل مباشر لجميع البطولات الكروية العالمية: دوري الأبطال والدوريات الأوروبية والعالمية.</desc>
  </programme>
</tv>