<?xml version="1.0" encoding="UTF-8"?>
<tv generator-info-name="AlwanSportsEPG">
  <channel id="alwan_sports">
    <display-name>Alwan Sports</display-name>
    <icon src="https://raw.githubusercontent.com/ayoubboukous27/beIN-Sports-EPG-Worldwide/refs/heads/main/Logos/alwan-sports.png"/>
  </channel>
  <programme start="20260502145428 +0000" stop="20260502155428 +0000" channel="alwan_sports">
    <title>البطولات الكروية مباشرة</title>
    <desc>نقل مباشر لجميع البطولات الكروية العالمية: دوري الأبطال والدوريات الأوروبية والعالمية.</desc>
  </programme>
  <programme start="20260502155428 +0000" stop="20260502165428 +0000" channel="alwan_sports">
    <title>البطولات الكروية مباشرة</title>
    <desc>نقل مباشر لجميع البطولات الكروية العالمية: دوري الأبطال والدوريات الأوروبية والعالمية.</desc>
  </programme>
  <programme start="20260502165428 +0000" stop="20260502175428 +0000" channel="alwan_sports">
    <title>البطولات الكروية مباشرة</title>
    <desc>نقل مباشر لجميع البطولات الكروية العالمية: دوري الأبطال والدوريات الأوروبية والعالمية.</desc>
  </programme>
  <programme start="20260502175428 +0000" stop="20260502185428 +0000" channel="alwan_sports">
    <title>البطولات الكروية مباشرة</title>
    <desc>نقل مباشر لجميع البطولات الكروية العالمية: دوري الأبطال والدوريات الأوروبية والعالمية.</desc>
  </programme>
  <programme start="20260502185428 +0000" stop="20260502195428 +0000" channel="alwan_sports">
    <title>البطولات الكروية مباشرة</title>
    <desc>نقل مباشر لجميع البطولات الكروية العالمية: دوري الأبطال والدوريات الأوروبية والعالمية.</desc>
  </programme>
  <programme start="20260502195428 +0000" stop="20260502205428 +0000" channel="alwan_sports">
    <title>البطولات الكروية مباشرة</title>
    <desc>نقل مباشر لجميع البطولات الكروية العالمية: دوري الأبطال والدوريات الأوروبية والعالمية.</desc>
  </programme>
  <programme start="20260502205428 +0000" stop="20260502215428 +0000" channel="alwan_sports">
    <title>البطولات الكروية مباشرة</title>
    <desc>نقل مباشر لجميع البطولات الكروية العالمية: دوري الأبطال والدوريات الأوروبية والعالمية.</desc>
  </programme>
  <programme start="20260502215428 +0000" stop="20260502225428 +0000" channel="alwan_sports">
    <title>البطولات الكروية مباشرة</title>
    <desc>نقل مباشر لجميع البطولات الكروية العالمية: دوري الأبطال والدوريات الأوروبية والعالمية.</desc>
  </programme>
  <programme start="20260502225428 +0000" stop="20260502235428 +0000" channel="alwan_sports">
    <title>البطولات الكروية مباشرة</title>
    <desc>نقل مباشر لجميع البطولات الكروية العالمية: دوري الأبطال والدوريات الأوروبية والعالمية.</desc>
  </programme>
  <programme start="20260502235428 +0000" stop="20260503005428 +0000" channel="alwan_sports">
    <title>البطولات الكروية مباشرة</title>
    <desc>نقل مباشر لجميع البطولات الكروية العالمية: دوري الأبطال والدوريات الأوروبية والعالمية.</desc>
  </programme>
  <programme start="20260503005428 +0000" stop="20260503015428 +0000" channel="alwan_sports">
    <title>البطولات الكروية مباشرة</title>
    <desc>نقل مباشر لجميع البطولات الكروية العالمية: دوري الأبطال والدوريات الأوروبية والعالمية.</desc>
  </programme>
  <programme start="20260503015428 +0000" stop="20260503025428 +0000" channel="alwan_sports">
    <title>البطولات الكروية مباشرة</title>
    <desc>نقل مباشر لجميع البطولات الكروية العالمية: دوري الأبطال والدوريات الأوروبية والعالمية.</desc>
  </programme>
  <programme start="20260503025428 +0000" stop="20260503035428 +0000" channel="alwan_sports">
    <title>البطولات الكروية مباشرة</title>
    <desc>نقل مباشر لجميع البطولات الكروية العالمية: دوري الأبطال والدوريات الأوروبية والعالمية.</desc>
  </programme>
  <programme start="20260503035428 +0000" stop="20260503045428 +0000" channel="alwan_sports">
    <title>البطولات الكروية مباشرة</title>
    <desc>نقل مباشر لجميع البطولات الكروية العالمية: دوري الأبطال والدوريات الأوروبية والعالمية.</desc>
  </programme>
  <programme start="20260503045428 +0000" stop="20260503055428 +0000" channel="alwan_sports">
    <title>البطولات الكروية مباشرة</title>
    <desc>نقل مباشر لجميع البطولات الكروية العالمية: دوري الأبطال والدوريات الأوروبية والعالمية.</desc>
  </programme>
  <programme start="20260503055428 +0000" stop="20260503065428 +0000" channel="alwan_sports">
    <title>البطولات الكروية مباشرة</title>
    <desc>نقل مباشر لجميع البطولات الكروية العالمية: دوري الأبطال والدوريات الأوروبية والعالمية.</desc>
  </programme>
  <programme start="20260503065428 +0000" stop="20260503075428 +0000" channel="alwan_sports">
    <title>البطولات الكروية مباشرة</title>
    <desc>نقل مباشر لجميع البطولات الكروية العالمية: دوري الأبطال والدوريات الأوروبية والعالمية.</desc>
  </programme>
  <programme start="20260503075428 +0000" stop="20260503085428 +0000" channel="alwan_sports">
    <title>البطولات الكروية مباشرة</title>
    <desc>نقل مباشر لجميع البطولات الكروية العالمية: دوري الأبطال والدوريات الأوروبية والعالمية.</desc>
  </programme>
  <programme start="20260503085428 +0000" stop="20260503095428 +0000" channel="alwan_sports">
    <title>البطولات الكروية مباشرة</title>
    <desc>نقل مباشر لجميع البطولات الكروية العالمية: دوري الأبطال والدوريات الأوروبية والعالمية.</desc>
  </programme>
  <programme start="20260503095428 +0000" stop="20260503105428 +0000" channel="alwan_sports">
    <title>البطولات الكروية مباشرة</title>
    <desc>نقل مباشر لجميع البطولات الكروية العالمية: دوري الأبطال والدوريات الأوروبية والعالمية.</desc>
  </programme>
  <programme start="20260503105428 +0000" stop="20260503115428 +0000" channel="alwan_sports">
    <title>البطولات الكروية مباشرة</title>
    <desc>نقل مباشر لجميع البطولات الكروية العالمية: دوري الأبطال والدوريات الأوروبية والعالمية.</desc>
  </programme>
  <programme start="20260503115428 +0000" stop="20260503125428 +0000" channel="alwan_sports">
    <title>البطولات الكروية مباشرة</title>
    <desc>نقل مباشر لجميع البطولات الكروية العالمية: دوري الأبطال والدوريات الأوروبية والعالمية.</desc>
  </programme>
  <programme start="20260503125428 +0000" stop="20260503135428 +0000" channel="alwan_sports">
    <title>البطولات الكروية مباشرة</title>
    <desc>نقل مباشر لجميع البطولات الكروية العالمية: دوري الأبطال والدوريات الأوروبية والعالمية.</desc>
  </programme>
  <programme start="20260503135428 +0000" stop="20260503145428 +0000" channel="alwan_sports">
    <title>البطولات الكروية مباشرة</title>
    <desc>نقل مباشر لجميع البطولات الكروية العالمية: دوري الأبطال والدوريات الأوروبية والعالمية.</desc>
  </programme>
  <programme start="20260503145428 +0000" stop="20260503155428 +0000" channel="alwan_sports">
    <title>البطولات الكروية مباشرة</title>
    <desc>نقل مباشر لجميع البطولات الكروية العالمية: دوري الأبطال والدوريات الأوروبية والعالمية.</desc>
  </programme>
  <programme start="20260503155428 +0000" stop="20260503165428 +0000" channel="alwan_sports">
    <title>البطولات الكروية مباشرة</title>
    <desc>نقل مباشر لجميع البطولات الكروية العالمية: دوري الأبطال والدوريات الأوروبية والعالمية.</desc>
  </programme>
  <programme start="20260503165428 +0000" stop="20260503175428 +0000" channel="alwan_sports">
    <title>البطولات الكروية مباشرة</title>
    <desc>نقل مباشر لجميع البطولات الكروية العالمية: دوري الأبطال والدوريات الأوروبية والعالمية.</desc>
  </programme>
  <programme start="20260503175428 +0000" stop="20260503185428 +0000" channel="alwan_sports">
    <title>البطولات الكروية مباشرة</title>
    <desc>نقل مباشر لجميع البطولات الكروية العالمية: دوري الأبطال والدوريات الأوروبية والعالمية.</desc>
  </programme>
  <programme start="20260503185428 +0000" stop="20260503195428 +0000" channel="alwan_sports">
    <title>البطولات الكروية مباشرة</title>
    <desc>نقل مباشر لجميع البطولات الكروية العالمية: دوري الأبطال والدوريات الأوروبية والعالمية.</desc>
  </programme>
  <programme start="20260503195428 +0000" stop="20260503205428 +0000" channel="alwan_sports">
    <title>البطولات الكروية مباشرة</title>
    <desc>نقل مباشر لجميع البطولات الكروية العالمية: دوري الأبطال والدوريات الأوروبية والعالمية.</desc>
  </programme>
  <programme start="20260503205428 +0000" stop="20260503215428 +0000" channel="alwan_sports">
    <title>البطولات الكروية مباشرة</title>
    <desc>نقل مباشر لجميع البطولات الكروية العالمية: دوري الأبطال والدوريات الأوروبية والعالمية.</desc>
  </programme>
  <programme start="20260503215428 +0000" stop="20260503225428 +0000" channel="alwan_sports">
    <title>البطولات الكروية مباشرة</title>
    <desc>نقل مباشر لجميع البطولات الكروية العالمية: دوري الأبطال والدوريات الأوروبية والعالمية.</desc>
  </programme>
  <programme start="20260503225428 +0000" stop="20260503235428 +0000" channel="alwan_sports">
    <title>البطولات الكروية مباشرة</title>
    <desc>نقل مباشر لجميع البطولات الكروية العالمية: دوري الأبطال والدوريات الأوروبية والعالمية.</desc>
  </programme>
  <programme start="20260503235428 +0000" stop="20260504005428 +0000" channel="alwan_sports">
    <title>البطولات الكروية مباشرة</title>
    <desc>نقل مباشر لجميع البطولات الكروية العالمية: دوري الأبطال والدوريات الأوروبية والعالمية.</desc>
  </programme>
  <programme start="20260504005428 +0000" stop="20260504015428 +0000" channel="alwan_sports">
    <title>البطولات الكروية مباشرة</title>
    <desc>نقل مباشر لجميع البطولات الكروية العالمية: دوري الأبطال والدوريات الأوروبية والعالمية.</desc>
  </programme>
  <programme start="20260504015428 +0000" stop="20260504025428 +0000" channel="alwan_sports">
    <title>البطولات الكروية مباشرة</title>
    <desc>نقل مباشر لجميع البطولات الكروية العالمية: دوري الأبطال والدوريات الأوروبية والعالمية.</desc>
  </programme>
  <programme start="20260504025428 +0000" stop="20260504035428 +0000" channel="alwan_sports">
    <title>البطولات الكروية مباشرة</title>
    <desc>نقل مباشر لجميع البطولات الكروية العالمية: دوري الأبطال والدوريات الأوروبية والعالمية.</desc>
  </programme>
  <programme start="20260504035428 +0000" stop="20260504045428 +0000" channel="alwan_sports">
    <title>البطولات الكروية مباشرة</title>
    <desc>نقل مباشر لجميع البطولات الكروية العالمية: دوري الأبطال والدوريات الأوروبية والعالمية.</desc>
  </programme>
  <programme start="20260504045428 +0000" stop="20260504055428 +0000" channel="alwan_sports">
    <title>البطولات الكروية مباشرة</title>
    <desc>نقل مباشر لجميع البطولات الكروية العالمية: دوري الأبطال والدوريات الأوروبية والعالمية.</desc>
  </programme>
  <programme start="20260504055428 +0000" stop="20260504065428 +0000" channel="alwan_sports">
    <title>البطولات الكروية مباشرة</title>
    <desc>نقل مباشر لجميع البطولات الكروية العالمية: دوري الأبطال والدوريات الأوروبية والعالمية.</desc>
  </programme>
  <programme start="20260504065428 +0000" stop="20260504075428 +0000" channel="alwan_sports">
    <title>البطولات الكروية مباشرة</title>
    <desc>نقل مباشر لجميع البطولات الكروية العالمية: دوري الأبطال والدوريات الأوروبية والعالمية.</desc>
  </programme>
  <programme start="20260504075428 +0000" stop="20260504085428 +0000" channel="alwan_sports">
    <title>البطولات الكروية مباشرة</title>
    <desc>نقل مباشر لجميع البطولات الكروية العالمية: دوري الأبطال والدوريات الأوروبية والعالمية.</desc>
  </programme>
  <programme start="20260504085428 +0000" stop="20260504095428 +0000" channel="alwan_sports">
    <title>البطولات الكروية مباشرة</title>
    <desc>نقل مباشر لجميع البطولات الكروية العالمية: دوري الأبطال والدوريات الأوروبية والعالمية.</desc>
  </programme>
  <programme start="20260504095428 +0000" stop="20260504105428 +0000" channel="alwan_sports">
    <title>البطولات الكروية مباشرة</title>
    <desc>نقل مباشر لجميع البطولات الكروية العالمية: دوري الأبطال والدوريات الأوروبية والعالمية.</desc>
  </programme>
  <programme start="20260504105428 +0000" stop="20260504115428 +0000" channel="alwan_sports">
    <title>البطولات الكروية مباشرة</title>
    <desc>نقل مباشر لجميع البطولات الكروية العالمية: دوري الأبطال والدوريات الأوروبية والعالمية.</desc>
  </programme>
  <programme start="20260504115428 +0000" stop="20260504125428 +0000" channel="alwan_sports">
    <title>البطولات الكروية مباشرة</title>
    <desc>نقل مباشر لجميع البطولات الكروية العالمية: دوري الأبطال والدوريات الأوروبية والعالمية.</desc>
  </programme>
  <programme start="20260504125428 +0000" stop="20260504135428 +0000" channel="alwan_sports">
    <title>البطولات الكروية مباشرة</title>
    <desc>نقل مباشر لجميع البطولات الكروية العالمية: دوري الأبطال والدوريات الأوروبية والعالمية.</desc>
  </programme>
  <programme start="20260504135428 +0000" stop="20260504145428 +0000" channel="alwan_sports">
    <title>البطولات الكروية مباشرة</title>
    <desc>نقل مباشر لجميع البطولات الكروية العالمية: دوري الأبطال والدوريات الأوروبية والعالمية.</desc>
  </programme>
  <programme start="20260504145428 +0000" stop="20260504155428 +0000" channel="alwan_sports">
    <title>البطولات الكروية مباشرة</title>
    <desc>نقل مباشر لجميع البطولات الكروية العالمية: دوري الأبطال والدوريات الأوروبية والعالمية.</desc>
  </programme>
  <programme start="20260504155428 +0000" stop="20260504165428 +0000" channel="alwan_sports">
    <title>البطولات الكروية مباشرة</title>
    <desc>نقل مباشر لجميع البطولات الكروية العالمية: دوري الأبطال والدوريات الأوروبية والعالمية.</desc>
  </programme>
  <programme start="20260504165428 +0000" stop="20260504175428 +0000" channel="alwan_sports">
    <title>البطولات الكروية مباشرة</title>
    <desc>نقل مباشر لجميع البطولات الكروية العالمية: دوري الأبطال والدوريات الأوروبية والعالمية.</desc>
  </programme>
  <programme start="20260504175428 +0000" stop="20260504185428 +0000" channel="alwan_sports">
    <title>البطولات الكروية مباشرة</title>
    <desc>نقل مباشر لجميع البطولات الكروية العالمية: دوري الأبطال والدوريات الأوروبية والعالمية.</desc>
  </programme>
  <programme start="20260504185428 +0000" stop="20260504195428 +0000" channel="alwan_sports">
    <title>البطولات الكروية مباشرة</title>
    <desc>نقل مباشر لجميع البطولات الكروية العالمية: دوري الأبطال والدوريات الأوروبية والعالمية.</desc>
  </programme>
  <programme start="20260504195428 +0000" stop="20260504205428 +0000" channel="alwan_sports">
    <title>البطولات الكروية مباشرة</title>
    <desc>نقل مباشر لجميع البطولات الكروية العالمية: دوري الأبطال والدوريات الأوروبية والعالمية.</desc>
  </programme>
  <programme start="20260504205428 +0000" stop="20260504215428 +0000" channel="alwan_sports">
    <title>البطولات الكروية مباشرة</title>
    <desc>نقل مباشر لجميع البطولات الكروية العالمية: دوري الأبطال والدوريات الأوروبية والعالمية.</desc>
  </programme>
  <programme start="20260504215428 +0000" stop="20260504225428 +0000" channel="alwan_sports">
    <title>البطولات الكروية مباشرة</title>
    <desc>نقل مباشر لجميع البطولات الكروية العالمية: دوري الأبطال والدوريات الأوروبية والعالمية.</desc>
  </programme>
  <programme start="20260504225428 +0000" stop="20260504235428 +0000" channel="alwan_sports">
    <title>البطولات الكروية مباشرة</title>
    <desc>نقل مباشر لجميع البطولات الكروية العالمية: دوري الأبطال والدوريات الأوروبية والعالمية.</desc>
  </programme>
  <programme start="20260504235428 +0000" stop="20260505005428 +0000" channel="alwan_sports">
    <title>البطولات الكروية مباشرة</title>
    <desc>نقل مباشر لجميع البطولات الكروية العالمية: دوري الأبطال والدوريات الأوروبية والعالمية.</desc>
  </programme>
  <programme start="20260505005428 +0000" stop="20260505015428 +0000" channel="alwan_sports">
    <title>البطولات الكروية مباشرة</title>
    <desc>نقل مباشر لجميع البطولات الكروية العالمية: دوري الأبطال والدوريات الأوروبية والعالمية.</desc>
  </programme>
  <programme start="20260505015428 +0000" stop="20260505025428 +0000" channel="alwan_sports">
    <title>البطولات الكروية مباشرة</title>
    <desc>نقل مباشر لجميع البطولات الكروية العالمية: دوري الأبطال والدوريات الأوروبية والعالمية.</desc>
  </programme>
  <programme start="20260505025428 +0000" stop="20260505035428 +0000" channel="alwan_sports">
    <title>البطولات الكروية مباشرة</title>
    <desc>نقل مباشر لجميع البطولات الكروية العالمية: دوري الأبطال والدوريات الأوروبية والعالمية.</desc>
  </programme>
  <programme start="20260505035428 +0000" stop="20260505045428 +0000" channel="alwan_sports">
    <title>البطولات الكروية مباشرة</title>
    <desc>نقل مباشر لجميع البطولات الكروية العالمية: دوري الأبطال والدوريات الأوروبية والعالمية.</desc>
  </programme>
  <programme start="20260505045428 +0000" stop="20260505055428 +0000" channel="alwan_sports">
    <title>البطولات الكروية مباشرة</title>
    <desc>نقل مباشر لجميع البطولات الكروية العالمية: دوري الأبطال والدوريات الأوروبية والعالمية.</desc>
  </programme>
  <programme start="20260505055428 +0000" stop="20260505065428 +0000" channel="alwan_sports">
    <title>البطولات الكروية مباشرة</title>
    <desc>نقل مباشر لجميع البطولات الكروية العالمية: دوري الأبطال والدوريات الأوروبية والعالمية.</desc>
  </programme>
  <programme start="20260505065428 +0000" stop="20260505075428 +0000" channel="alwan_sports">
    <title>البطولات الكروية مباشرة</title>
    <desc>نقل مباشر لجميع البطولات الكروية العالمية: دوري الأبطال والدوريات الأوروبية والعالمية.</desc>
  </programme>
  <programme start="20260505075428 +0000" stop="20260505085428 +0000" channel="alwan_sports">
    <title>البطولات الكروية مباشرة</title>
    <desc>نقل مباشر لجميع البطولات الكروية العالمية: دوري الأبطال والدوريات الأوروبية والعالمية.</desc>
  </programme>
  <programme start="20260505085428 +0000" stop="20260505095428 +0000" channel="alwan_sports">
    <title>البطولات الكروية مباشرة</title>
    <desc>نقل مباشر لجميع البطولات الكروية العالمية: دوري الأبطال والدوريات الأوروبية والعالمية.</desc>
  </programme>
  <programme start="20260505095428 +0000" stop="20260505105428 +0000" channel="alwan_sports">
    <title>البطولات الكروية مباشرة</title>
    <desc>نقل مباشر لجميع البطولات الكروية العالمية: دوري الأبطال والدوريات الأوروبية والعالمية.</desc>
  </programme>
  <programme start="20260505105428 +0000" stop="20260505115428 +0000" channel="alwan_sports">
    <title>البطولات الكروية مباشرة</title>
    <desc>نقل مباشر لجميع البطولات الكروية العالمية: دوري الأبطال والدوريات الأوروبية والعالمية.</desc>
  </programme>
  <programme start="20260505115428 +0000" stop="20260505125428 +0000" channel="alwan_sports">
    <title>البطولات الكروية مباشرة</title>
    <desc>نقل مباشر لجميع البطولات الكروية العالمية: دوري الأبطال والدوريات الأوروبية والعالمية.</desc>
  </programme>
  <programme start="20260505125428 +0000" stop="20260505135428 +0000" channel="alwan_sports">
    <title>البطولات الكروية مباشرة</title>
    <desc>نقل مباشر لجميع البطولات الكروية العالمية: دوري الأبطال والدوريات الأوروبية والعالمية.</desc>
  </programme>
  <programme start="20260505135428 +0000" stop="20260505145428 +0000" channel="alwan_sports">
    <title>البطولات الكروية مباشرة</title>
    <desc>نقل مباشر لجميع البطولات الكروية العالمية: دوري الأبطال والدوريات الأوروبية والعالمية.</desc>
  </programme>
  <programme start="20260505145428 +0000" stop="20260505155428 +0000" channel="alwan_sports">
    <title>البطولات الكروية مباشرة</title>
    <desc>نقل مباشر لجميع البطولات الكروية العالمية: دوري الأبطال والدوريات الأوروبية والعالمية.</desc>
  </programme>
  <programme start="20260505155428 +0000" stop="20260505165428 +0000" channel="alwan_sports">
    <title>البطولات الكروية مباشرة</title>
    <desc>نقل مباشر لجميع البطولات الكروية العالمية: دوري الأبطال والدوريات الأوروبية والعالمية.</desc>
  </programme>
  <programme start="20260505165428 +0000" stop="20260505175428 +0000" channel="alwan_sports">
    <title>البطولات الكروية مباشرة</title>
    <desc>نقل مباشر لجميع البطولات الكروية العالمية: دوري الأبطال والدوريات الأوروبية والعالمية.</desc>
  </programme>
  <programme start="20260505175428 +0000" stop="20260505185428 +0000" channel="alwan_sports">
    <title>البطولات الكروية مباشرة</title>
    <desc>نقل مباشر لجميع البطولات الكروية العالمية: دوري الأبطال والدوريات الأوروبية والعالمية.</desc>
  </programme>
  <programme start="20260505185428 +0000" stop="20260505195428 +0000" channel="alwan_sports">
    <title>البطولات الكروية مباشرة</title>
    <desc>نقل مباشر لجميع البطولات الكروية العالمية: دوري الأبطال والدوريات الأوروبية والعالمية.</desc>
  </programme>
  <programme start="20260505195428 +0000" stop="20260505205428 +0000" channel="alwan_sports">
    <title>البطولات الكروية مباشرة</title>
    <desc>نقل مباشر لجميع البطولات الكروية العالمية: دوري الأبطال والدوريات الأوروبية والعالمية.</desc>
  </programme>
  <programme start="20260505205428 +0000" stop="20260505215428 +0000" channel="alwan_sports">
    <title>البطولات الكروية مباشرة</title>
    <desc>نقل مباشر لجميع البطولات الكروية العالمية: دوري الأبطال والدوريات الأوروبية والعالمية.</desc>
  </programme>
  <programme start="20260505215428 +0000" stop="20260505225428 +0000" channel="alwan_sports">
    <title>البطولات الكروية مباشرة</title>
    <desc>نقل مباشر لجميع البطولات الكروية العالمية: دوري الأبطال والدوريات الأوروبية والعالمية.</desc>
  </programme>
  <programme start="20260505225428 +0000" stop="20260505235428 +0000" channel="alwan_sports">
    <title>البطولات الكروية مباشرة</title>
    <desc>نقل مباشر لجميع البطولات الكروية العالمية: دوري الأبطال والدوريات الأوروبية والعالمية.</desc>
  </programme>
  <programme start="20260505235428 +0000" stop="20260506005428 +0000" channel="alwan_sports">
    <title>البطولات الكروية مباشرة</title>
    <desc>نقل مباشر لجميع البطولات الكروية العالمية: دوري الأبطال والدوريات الأوروبية والعالمية.</desc>
  </programme>
  <programme start="20260506005428 +0000" stop="20260506015428 +0000" channel="alwan_sports">
    <title>البطولات الكروية مباشرة</title>
    <desc>نقل مباشر لجميع البطولات الكروية العالمية: دوري الأبطال والدوريات الأوروبية والعالمية.</desc>
  </programme>
  <programme start="20260506015428 +0000" stop="20260506025428 +0000" channel="alwan_sports">
    <title>البطولات الكروية مباشرة</title>
    <desc>نقل مباشر لجميع البطولات الكروية العالمية: دوري الأبطال والدوريات الأوروبية والعالمية.</desc>
  </programme>
  <programme start="20260506025428 +0000" stop="20260506035428 +0000" channel="alwan_sports">
    <title>البطولات الكروية مباشرة</title>
    <desc>نقل مباشر لجميع البطولات الكروية العالمية: دوري الأبطال والدوريات الأوروبية والعالمية.</desc>
  </programme>
  <programme start="20260506035428 +0000" stop="20260506045428 +0000" channel="alwan_sports">
    <title>البطولات الكروية مباشرة</title>
    <desc>نقل مباشر لجميع البطولات الكروية العالمية: دوري الأبطال والدوريات الأوروبية والعالمية.</desc>
  </programme>
  <programme start="20260506045428 +0000" stop="20260506055428 +0000" channel="alwan_sports">
    <title>البطولات الكروية مباشرة</title>
    <desc>نقل مباشر لجميع البطولات الكروية العالمية: دوري الأبطال والدوريات الأوروبية والعالمية.</desc>
  </programme>
  <programme start="20260506055428 +0000" stop="20260506065428 +0000" channel="alwan_sports">
    <title>البطولات الكروية مباشرة</title>
    <desc>نقل مباشر لجميع البطولات الكروية العالمية: دوري الأبطال والدوريات الأوروبية والعالمية.</desc>
  </programme>
  <programme start="20260506065428 +0000" stop="20260506075428 +0000" channel="alwan_sports">
    <title>البطولات الكروية مباشرة</title>
    <desc>نقل مباشر لجميع البطولات الكروية العالمية: دوري الأبطال والدوريات الأوروبية والعالمية.</desc>
  </programme>
  <programme start="20260506075428 +0000" stop="20260506085428 +0000" channel="alwan_sports">
    <title>البطولات الكروية مباشرة</title>
    <desc>نقل مباشر لجميع البطولات الكروية العالمية: دوري الأبطال والدوريات الأوروبية والعالمية.</desc>
  </programme>
  <programme start="20260506085428 +0000" stop="20260506095428 +0000" channel="alwan_sports">
    <title>البطولات الكروية مباشرة</title>
    <desc>نقل مباشر لجميع البطولات الكروية العالمية: دوري الأبطال والدوريات الأوروبية والعالمية.</desc>
  </programme>
  <programme start="20260506095428 +0000" stop="20260506105428 +0000" channel="alwan_sports">
    <title>البطولات الكروية مباشرة</title>
    <desc>نقل مباشر لجميع البطولات الكروية العالمية: دوري الأبطال والدوريات الأوروبية والعالمية.</desc>
  </programme>
  <programme start="20260506105428 +0000" stop="20260506115428 +0000" channel="alwan_sports">
    <title>البطولات الكروية مباشرة</title>
    <desc>نقل مباشر لجميع البطولات الكروية العالمية: دوري الأبطال والدوريات الأوروبية والعالمية.</desc>
  </programme>
  <programme start="20260506115428 +0000" stop="20260506125428 +0000" channel="alwan_sports">
    <title>البطولات الكروية مباشرة</title>
    <desc>نقل مباشر لجميع البطولات الكروية العالمية: دوري الأبطال والدوريات الأوروبية والعالمية.</desc>
  </programme>
  <programme start="20260506125428 +0000" stop="20260506135428 +0000" channel="alwan_sports">
    <title>البطولات الكروية مباشرة</title>
    <desc>نقل مباشر لجميع البطولات الكروية العالمية: دوري الأبطال والدوريات الأوروبية والعالمية.</desc>
  </programme>
  <programme start="20260506135428 +0000" stop="20260506145428 +0000" channel="alwan_sports">
    <title>البطولات الكروية مباشرة</title>
    <desc>نقل مباشر لجميع البطولات الكروية العالمية: دوري الأبطال والدوريات الأوروبية والعالمية.</desc>
  </programme>
  <programme start="20260506145428 +0000" stop="20260506155428 +0000" channel="alwan_sports">
    <title>البطولات الكروية مباشرة</title>
    <desc>نقل مباشر لجميع البطولات الكروية العالمية: دوري الأبطال والدوريات الأوروبية والعالمية.</desc>
  </programme>
  <programme start="20260506155428 +0000" stop="20260506165428 +0000" channel="alwan_sports">
    <title>البطولات الكروية مباشرة</title>
    <desc>نقل مباشر لجميع البطولات الكروية العالمية: دوري الأبطال والدوريات الأوروبية والعالمية.</desc>
  </programme>
  <programme start="20260506165428 +0000" stop="20260506175428 +0000" channel="alwan_sports">
    <title>البطولات الكروية مباشرة</title>
    <desc>نقل مباشر لجميع البطولات الكروية العالمية: دوري الأبطال والدوريات الأوروبية والعالمية.</desc>
  </programme>
  <programme start="20260506175428 +0000" stop="20260506185428 +0000" channel="alwan_sports">
    <title>البطولات الكروية مباشرة</title>
    <desc>نقل مباشر لجميع البطولات الكروية العالمية: دوري الأبطال والدوريات الأوروبية والعالمية.</desc>
  </programme>
  <programme start="20260506185428 +0000" stop="20260506195428 +0000" channel="alwan_sports">
    <title>البطولات الكروية مباشرة</title>
    <desc>نقل مباشر لجميع البطولات الكروية العالمية: دوري الأبطال والدوريات الأوروبية والعالمية.</desc>
  </programme>
  <programme start="20260506195428 +0000" stop="20260506205428 +0000" channel="alwan_sports">
    <title>البطولات الكروية مباشرة</title>
    <desc>نقل مباشر لجميع البطولات الكروية العالمية: دوري الأبطال والدوريات الأوروبية والعالمية.</desc>
  </programme>
  <programme start="20260506205428 +0000" stop="20260506215428 +0000" channel="alwan_sports">
    <title>البطولات الكروية مباشرة</title>
    <desc>نقل مباشر لجميع البطولات الكروية العالمية: دوري الأبطال والدوريات الأوروبية والعالمية.</desc>
  </programme>
  <programme start="20260506215428 +0000" stop="20260506225428 +0000" channel="alwan_sports">
    <title>البطولات الكروية مباشرة</title>
    <desc>نقل مباشر لجميع البطولات الكروية العالمية: دوري الأبطال والدوريات الأوروبية والعالمية.</desc>
  </programme>
  <programme start="20260506225428 +0000" stop="20260506235428 +0000" channel="alwan_sports">
    <title>البطولات الكروية مباشرة</title>
    <desc>نقل مباشر لجميع البطولات الكروية العالمية: دوري الأبطال والدوريات الأوروبية والعالمية.</desc>
  </programme>
  <programme start="20260506235428 +0000" stop="20260507005428 +0000" channel="alwan_sports">
    <title>البطولات الكروية مباشرة</title>
    <desc>نقل مباشر لجميع البطولات الكروية العالمية: دوري الأبطال والدوريات الأوروبية والعالمية.</desc>
  </programme>
  <programme start="20260507005428 +0000" stop="20260507015428 +0000" channel="alwan_sports">
    <title>البطولات الكروية مباشرة</title>
    <desc>نقل مباشر لجميع البطولات الكروية العالمية: دوري الأبطال والدوريات الأوروبية والعالمية.</desc>
  </programme>
  <programme start="20260507015428 +0000" stop="20260507025428 +0000" channel="alwan_sports">
    <title>البطولات الكروية مباشرة</title>
    <desc>نقل مباشر لجميع البطولات الكروية العالمية: دوري الأبطال والدوريات الأوروبية والعالمية.</desc>
  </programme>
  <programme start="20260507025428 +0000" stop="20260507035428 +0000" channel="alwan_sports">
    <title>البطولات الكروية مباشرة</title>
    <desc>نقل مباشر لجميع البطولات الكروية العالمية: دوري الأبطال والدوريات الأوروبية والعالمية.</desc>
  </programme>
  <programme start="20260507035428 +0000" stop="20260507045428 +0000" channel="alwan_sports">
    <title>البطولات الكروية مباشرة</title>
    <desc>نقل مباشر لجميع البطولات الكروية العالمية: دوري الأبطال والدوريات الأوروبية والعالمية.</desc>
  </programme>
  <programme start="20260507045428 +0000" stop="20260507055428 +0000" channel="alwan_sports">
    <title>البطولات الكروية مباشرة</title>
    <desc>نقل مباشر لجميع البطولات الكروية العالمية: دوري الأبطال والدوريات الأوروبية والعالمية.</desc>
  </programme>
  <programme start="20260507055428 +0000" stop="20260507065428 +0000" channel="alwan_sports">
    <title>البطولات الكروية مباشرة</title>
    <desc>نقل مباشر لجميع البطولات الكروية العالمية: دوري الأبطال والدوريات الأوروبية والعالمية.</desc>
  </programme>
  <programme start="20260507065428 +0000" stop="20260507075428 +0000" channel="alwan_sports">
    <title>البطولات الكروية مباشرة</title>
    <desc>نقل مباشر لجميع البطولات الكروية العالمية: دوري الأبطال والدوريات الأوروبية والعالمية.</desc>
  </programme>
  <programme start="20260507075428 +0000" stop="20260507085428 +0000" channel="alwan_sports">
    <title>البطولات الكروية مباشرة</title>
    <desc>نقل مباشر لجميع البطولات الكروية العالمية: دوري الأبطال والدوريات الأوروبية والعالمية.</desc>
  </programme>
  <programme start="20260507085428 +0000" stop="20260507095428 +0000" channel="alwan_sports">
    <title>البطولات الكروية مباشرة</title>
    <desc>نقل مباشر لجميع البطولات الكروية العالمية: دوري الأبطال والدوريات الأوروبية والعالمية.</desc>
  </programme>
  <programme start="20260507095428 +0000" stop="20260507105428 +0000" channel="alwan_sports">
    <title>البطولات الكروية مباشرة</title>
    <desc>نقل مباشر لجميع البطولات الكروية العالمية: دوري الأبطال والدوريات الأوروبية والعالمية.</desc>
  </programme>
  <programme start="20260507105428 +0000" stop="20260507115428 +0000" channel="alwan_sports">
    <title>البطولات الكروية مباشرة</title>
    <desc>نقل مباشر لجميع البطولات الكروية العالمية: دوري الأبطال والدوريات الأوروبية والعالمية.</desc>
  </programme>
  <programme start="20260507115428 +0000" stop="20260507125428 +0000" channel="alwan_sports">
    <title>البطولات الكروية مباشرة</title>
    <desc>نقل مباشر لجميع البطولات الكروية العالمية: دوري الأبطال والدوريات الأوروبية والعالمية.</desc>
  </programme>
  <programme start="20260507125428 +0000" stop="20260507135428 +0000" channel="alwan_sports">
    <title>البطولات الكروية مباشرة</title>
    <desc>نقل مباشر لجميع البطولات الكروية العالمية: دوري الأبطال والدوريات الأوروبية والعالمية.</desc>
  </programme>
  <programme start="20260507135428 +0000" stop="20260507145428 +0000" channel="alwan_sports">
    <title>البطولات الكروية مباشرة</title>
    <desc>نقل مباشر لجميع البطولات الكروية العالمية: دوري الأبطال والدوريات الأوروبية والعالمية.</desc>
  </programme>
  <programme start="20260507145428 +0000" stop="20260507155428 +0000" channel="alwan_sports">
    <title>البطولات الكروية مباشرة</title>
    <desc>نقل مباشر لجميع البطولات الكروية العالمية: دوري الأبطال والدوريات الأوروبية والعالمية.</desc>
  </programme>
  <programme start="20260507155428 +0000" stop="20260507165428 +0000" channel="alwan_sports">
    <title>البطولات الكروية مباشرة</title>
    <desc>نقل مباشر لجميع البطولات الكروية العالمية: دوري الأبطال والدوريات الأوروبية والعالمية.</desc>
  </programme>
  <programme start="20260507165428 +0000" stop="20260507175428 +0000" channel="alwan_sports">
    <title>البطولات الكروية مباشرة</title>
    <desc>نقل مباشر لجميع البطولات الكروية العالمية: دوري الأبطال والدوريات الأوروبية والعالمية.</desc>
  </programme>
  <programme start="20260507175428 +0000" stop="20260507185428 +0000" channel="alwan_sports">
    <title>البطولات الكروية مباشرة</title>
    <desc>نقل مباشر لجميع البطولات الكروية العالمية: دوري الأبطال والدوريات الأوروبية والعالمية.</desc>
  </programme>
  <programme start="20260507185428 +0000" stop="20260507195428 +0000" channel="alwan_sports">
    <title>البطولات الكروية مباشرة</title>
    <desc>نقل مباشر لجميع البطولات الكروية العالمية: دوري الأبطال والدوريات الأوروبية والعالمية.</desc>
  </programme>
  <programme start="20260507195428 +0000" stop="20260507205428 +0000" channel="alwan_sports">
    <title>البطولات الكروية مباشرة</title>
    <desc>نقل مباشر لجميع البطولات الكروية العالمية: دوري الأبطال والدوريات الأوروبية والعالمية.</desc>
  </programme>
  <programme start="20260507205428 +0000" stop="20260507215428 +0000" channel="alwan_sports">
    <title>البطولات الكروية مباشرة</title>
    <desc>نقل مباشر لجميع البطولات الكروية العالمية: دوري الأبطال والدوريات الأوروبية والعالمية.</desc>
  </programme>
  <programme start="20260507215428 +0000" stop="20260507225428 +0000" channel="alwan_sports">
    <title>البطولات الكروية مباشرة</title>
    <desc>نقل مباشر لجميع البطولات الكروية العالمية: دوري الأبطال والدوريات الأوروبية والعالمية.</desc>
  </programme>
  <programme start="20260507225428 +0000" stop="20260507235428 +0000" channel="alwan_sports">
    <title>البطولات الكروية مباشرة</title>
    <desc>نقل مباشر لجميع البطولات الكروية العالمية: دوري الأبطال والدوريات الأوروبية والعالمية.</desc>
  </programme>
  <programme start="20260507235428 +0000" stop="20260508005428 +0000" channel="alwan_sports">
    <title>البطولات الكروية مباشرة</title>
    <desc>نقل مباشر لجميع البطولات الكروية العالمية: دوري الأبطال والدوريات الأوروبية والعالمية.</desc>
  </programme>
  <programme start="20260508005428 +0000" stop="20260508015428 +0000" channel="alwan_sports">
    <title>البطولات الكروية مباشرة</title>
    <desc>نقل مباشر لجميع البطولات الكروية العالمية: دوري الأبطال والدوريات الأوروبية والعالمية.</desc>
  </programme>
  <programme start="20260508015428 +0000" stop="20260508025428 +0000" channel="alwan_sports">
    <title>البطولات الكروية مباشرة</title>
    <desc>نقل مباشر لجميع البطولات الكروية العالمية: دوري الأبطال والدوريات الأوروبية والعالمية.</desc>
  </programme>
  <programme start="20260508025428 +0000" stop="20260508035428 +0000" channel="alwan_sports">
    <title>البطولات الكروية مباشرة</title>
    <desc>نقل مباشر لجميع البطولات الكروية العالمية: دوري الأبطال والدوريات الأوروبية والعالمية.</desc>
  </programme>
  <programme start="20260508035428 +0000" stop="20260508045428 +0000" channel="alwan_sports">
    <title>البطولات الكروية مباشرة</title>
    <desc>نقل مباشر لجميع البطولات الكروية العالمية: دوري الأبطال والدوريات الأوروبية والعالمية.</desc>
  </programme>
  <programme start="20260508045428 +0000" stop="20260508055428 +0000" channel="alwan_sports">
    <title>البطولات الكروية مباشرة</title>
    <desc>نقل مباشر لجميع البطولات الكروية العالمية: دوري الأبطال والدوريات الأوروبية والعالمية.</desc>
  </programme>
  <programme start="20260508055428 +0000" stop="20260508065428 +0000" channel="alwan_sports">
    <title>البطولات الكروية مباشرة</title>
    <desc>نقل مباشر لجميع البطولات الكروية العالمية: دوري الأبطال والدوريات الأوروبية والعالمية.</desc>
  </programme>
  <programme start="20260508065428 +0000" stop="20260508075428 +0000" channel="alwan_sports">
    <title>البطولات الكروية مباشرة</title>
    <desc>نقل مباشر لجميع البطولات الكروية العالمية: دوري الأبطال والدوريات الأوروبية والعالمية.</desc>
  </programme>
  <programme start="20260508075428 +0000" stop="20260508085428 +0000" channel="alwan_sports">
    <title>البطولات الكروية مباشرة</title>
    <desc>نقل مباشر لجميع البطولات الكروية العالمية: دوري الأبطال والدوريات الأوروبية والعالمية.</desc>
  </programme>
  <programme start="20260508085428 +0000" stop="20260508095428 +0000" channel="alwan_sports">
    <title>البطولات الكروية مباشرة</title>
    <desc>نقل مباشر لجميع البطولات الكروية العالمية: دوري الأبطال والدوريات الأوروبية والعالمية.</desc>
  </programme>
  <programme start="20260508095428 +0000" stop="20260508105428 +0000" channel="alwan_sports">
    <title>البطولات الكروية مباشرة</title>
    <desc>نقل مباشر لجميع البطولات الكروية العالمية: دوري الأبطال والدوريات الأوروبية والعالمية.</desc>
  </programme>
  <programme start="20260508105428 +0000" stop="20260508115428 +0000" channel="alwan_sports">
    <title>البطولات الكروية مباشرة</title>
    <desc>نقل مباشر لجميع البطولات الكروية العالمية: دوري الأبطال والدوريات الأوروبية والعالمية.</desc>
  </programme>
  <programme start="20260508115428 +0000" stop="20260508125428 +0000" channel="alwan_sports">
    <title>البطولات الكروية مباشرة</title>
    <desc>نقل مباشر لجميع البطولات الكروية العالمية: دوري الأبطال والدوريات الأوروبية والعالمية.</desc>
  </programme>
  <programme start="20260508125428 +0000" stop="20260508135428 +0000" channel="alwan_sports">
    <title>البطولات الكروية مباشرة</title>
    <desc>نقل مباشر لجميع البطولات الكروية العالمية: دوري الأبطال والدوريات الأوروبية والعالمية.</desc>
  </programme>
  <programme start="20260508135428 +0000" stop="20260508145428 +0000" channel="alwan_sports">
    <title>البطولات الكروية مباشرة</title>
    <desc>نقل مباشر لجميع البطولات الكروية العالمية: دوري الأبطال والدوريات الأوروبية والعالمية.</desc>
  </programme>
  <programme start="20260508145428 +0000" stop="20260508155428 +0000" channel="alwan_sports">
    <title>البطولات الكروية مباشرة</title>
    <desc>نقل مباشر لجميع البطولات الكروية العالمية: دوري الأبطال والدوريات الأوروبية والعالمية.</desc>
  </programme>
  <programme start="20260508155428 +0000" stop="20260508165428 +0000" channel="alwan_sports">
    <title>البطولات الكروية مباشرة</title>
    <desc>نقل مباشر لجميع البطولات الكروية العالمية: دوري الأبطال والدوريات الأوروبية والعالمية.</desc>
  </programme>
  <programme start="20260508165428 +0000" stop="20260508175428 +0000" channel="alwan_sports">
    <title>البطولات الكروية مباشرة</title>
    <desc>نقل مباشر لجميع البطولات الكروية العالمية: دوري الأبطال والدوريات الأوروبية والعالمية.</desc>
  </programme>
  <programme start="20260508175428 +0000" stop="20260508185428 +0000" channel="alwan_sports">
    <title>البطولات الكروية مباشرة</title>
    <desc>نقل مباشر لجميع البطولات الكروية العالمية: دوري الأبطال والدوريات الأوروبية والعالمية.</desc>
  </programme>
  <programme start="20260508185428 +0000" stop="20260508195428 +0000" channel="alwan_sports">
    <title>البطولات الكروية مباشرة</title>
    <desc>نقل مباشر لجميع البطولات الكروية العالمية: دوري الأبطال والدوريات الأوروبية والعالمية.</desc>
  </programme>
  <programme start="20260508195428 +0000" stop="20260508205428 +0000" channel="alwan_sports">
    <title>البطولات الكروية مباشرة</title>
    <desc>نقل مباشر لجميع البطولات الكروية العالمية: دوري الأبطال والدوريات الأوروبية والعالمية.</desc>
  </programme>
  <programme start="20260508205428 +0000" stop="20260508215428 +0000" channel="alwan_sports">
    <title>البطولات الكروية مباشرة</title>
    <desc>نقل مباشر لجميع البطولات الكروية العالمية: دوري الأبطال والدوريات الأوروبية والعالمية.</desc>
  </programme>
  <programme start="20260508215428 +0000" stop="20260508225428 +0000" channel="alwan_sports">
    <title>البطولات الكروية مباشرة</title>
    <desc>نقل مباشر لجميع البطولات الكروية العالمية: دوري الأبطال والدوريات الأوروبية والعالمية.</desc>
  </programme>
  <programme start="20260508225428 +0000" stop="20260508235428 +0000" channel="alwan_sports">
    <title>البطولات الكروية مباشرة</title>
    <desc>نقل مباشر لجميع البطولات الكروية العالمية: دوري الأبطال والدوريات الأوروبية والعالمية.</desc>
  </programme>
  <programme start="20260508235428 +0000" stop="20260509005428 +0000" channel="alwan_sports">
    <title>البطولات الكروية مباشرة</title>
    <desc>نقل مباشر لجميع البطولات الكروية العالمية: دوري الأبطال والدوريات الأوروبية والعالمية.</desc>
  </programme>
  <programme start="20260509005428 +0000" stop="20260509015428 +0000" channel="alwan_sports">
    <title>البطولات الكروية مباشرة</title>
    <desc>نقل مباشر لجميع البطولات الكروية العالمية: دوري الأبطال والدوريات الأوروبية والعالمية.</desc>
  </programme>
  <programme start="20260509015428 +0000" stop="20260509025428 +0000" channel="alwan_sports">
    <title>البطولات الكروية مباشرة</title>
    <desc>نقل مباشر لجميع البطولات الكروية العالمية: دوري الأبطال والدوريات الأوروبية والعالمية.</desc>
  </programme>
  <programme start="20260509025428 +0000" stop="20260509035428 +0000" channel="alwan_sports">
    <title>البطولات الكروية مباشرة</title>
    <desc>نقل مباشر لجميع البطولات الكروية العالمية: دوري الأبطال والدوريات الأوروبية والعالمية.</desc>
  </programme>
  <programme start="20260509035428 +0000" stop="20260509045428 +0000" channel="alwan_sports">
    <title>البطولات الكروية مباشرة</title>
    <desc>نقل مباشر لجميع البطولات الكروية العالمية: دوري الأبطال والدوريات الأوروبية والعالمية.</desc>
  </programme>
  <programme start="20260509045428 +0000" stop="20260509055428 +0000" channel="alwan_sports">
    <title>البطولات الكروية مباشرة</title>
    <desc>نقل مباشر لجميع البطولات الكروية العالمية: دوري الأبطال والدوريات الأوروبية والعالمية.</desc>
  </programme>
  <programme start="20260509055428 +0000" stop="20260509065428 +0000" channel="alwan_sports">
    <title>البطولات الكروية مباشرة</title>
    <desc>نقل مباشر لجميع البطولات الكروية العالمية: دوري الأبطال والدوريات الأوروبية والعالمية.</desc>
  </programme>
  <programme start="20260509065428 +0000" stop="20260509075428 +0000" channel="alwan_sports">
    <title>البطولات الكروية مباشرة</title>
    <desc>نقل مباشر لجميع البطولات الكروية العالمية: دوري الأبطال والدوريات الأوروبية والعالمية.</desc>
  </programme>
  <programme start="20260509075428 +0000" stop="20260509085428 +0000" channel="alwan_sports">
    <title>البطولات الكروية مباشرة</title>
    <desc>نقل مباشر لجميع البطولات الكروية العالمية: دوري الأبطال والدوريات الأوروبية والعالمية.</desc>
  </programme>
  <programme start="20260509085428 +0000" stop="20260509095428 +0000" channel="alwan_sports">
    <title>البطولات الكروية مباشرة</title>
    <desc>نقل مباشر لجميع البطولات الكروية العالمية: دوري الأبطال والدوريات الأوروبية والعالمية.</desc>
  </programme>
  <programme start="20260509095428 +0000" stop="20260509105428 +0000" channel="alwan_sports">
    <title>البطولات الكروية مباشرة</title>
    <desc>نقل مباشر لجميع البطولات الكروية العالمية: دوري الأبطال والدوريات الأوروبية والعالمية.</desc>
  </programme>
  <programme start="20260509105428 +0000" stop="20260509115428 +0000" channel="alwan_sports">
    <title>البطولات الكروية مباشرة</title>
    <desc>نقل مباشر لجميع البطولات الكروية العالمية: دوري الأبطال والدوريات الأوروبية والعالمية.</desc>
  </programme>
  <programme start="20260509115428 +0000" stop="20260509125428 +0000" channel="alwan_sports">
    <title>البطولات الكروية مباشرة</title>
    <desc>نقل مباشر لجميع البطولات الكروية العالمية: دوري الأبطال والدوريات الأوروبية والعالمية.</desc>
  </programme>
  <programme start="20260509125428 +0000" stop="20260509135428 +0000" channel="alwan_sports">
    <title>البطولات الكروية مباشرة</title>
    <desc>نقل مباشر لجميع البطولات الكروية العالمية: دوري الأبطال والدوريات الأوروبية والعالمية.</desc>
  </programme>
  <programme start="20260509135428 +0000" stop="20260509145428 +0000" channel="alwan_sports">
    <title>البطولات الكروية مباشرة</title>
    <desc>نقل مباشر لجميع البطولات الكروية العالمية: دوري الأبطال والدوريات الأوروبية والعالمية.</desc>
  </programme>
</tv>